Workbook

Sheet BP
A1: Clube de Regatas do Flamengo — Balanço Patrimonial
A2: Valores em R$ milhares — 4 exercícios consecutivos (2022 a 2025)
A4: Linha | B4: Nota | C4: 2022 | D4: 2023 | E4: 2024 Cont. | F4: 2024 Consol. | G4: 2025 Cont. | H4: 2025 Consol.
A5: ATIVO
A6: Circulante
A7: Caixa e equivalentes de caixa | B7: 3 | C7: 236887 | D7: 234487 | E7: 70557 | F7: 91841 | G7: 143941 | H7: 191714
A8: Caixa restrito | B8: 3 | C8: 17581 | D8: 28073 | E8: 41662 | F8: 41662 | G8: 51140 | H8: 51140
A9: Contas a receber | B9: 4 | C9: 71541 | D9: 162109 | E9: 185416 | F9: 189501 | G9: 348380 | H9: 344409
A10: Estoques | D10: 3780 | E10: 1753 | F10: 1753 | G10: 1799 | H10: 1799
A11: Despesas antecipadas | D11: 11272 | E11: 8487 | F11: 8487 | G11: 5274 | H11: 6763
A12: Instrumentos financeiros (forwards) | B12: 23 | G12: 3086 | H12: 3086
A13: Outros | C13: 17549 | D13: 16193 | E13: 13995 | F13: 14099 | G13: 5346 | H13: 6064
A14: Total do ativo circulante | C14: =SUM(C7,C8,C9,C10,C11,C12,C13) -> 343558 | D14: =SUM(D7,D8,D9,D10,D11,D12,D13) -> 455914 | E14: =SUM(E7,E8,E9,E10,E11,E12,E13) -> 321870 | F14: =SUM(F7,F8,F9,F10,F11,F12,F13) -> 347343 | G14: =SUM(G7,G8,G9,G10,G11,G12,G13) -> 558966 | H14: =SUM(H7,H8,H9,H10,H11,H12,H13) -> 604975
A16: Ativo disponível para venda (Hilton Rio By Yoo) | B16: 6 | D16: 59953 | E16: 81377 | F16: 81377 | G16: 54220 | H16: 54220
A18: Não circulante
A19: Contas a receber LP (transferência jogadores) | B19: 4 | C19: 37034 | D19: 54196 | E19: 36066 | F19: 36066 | G19: 107905 | H19: 107905
A20: Depósitos judiciais | B20: 13 | C20: 53076 | D20: 58780 | E20: 49969 | F20: 49969 | G20: 23598 | H20: 23598
A21: Investimento em participação societária (Fla-Flu) | B21: 5 | E21: 2401 | G21: 6390
A22: Propriedades para investimento | C22: 104893 | D22: 38625 | E22: 171 | F22: 171
A23: Imobilizado | B23: 8 | C23: 216165 | D23: 247794 | E23: 427509 | F23: 427965 | G23: 440614 | H23: 441424
A24: Intangível | B24: 7 | C24: 372299 | D24: 469080 | E24: 605405 | F24: 782747 | G24: 800619 | H24: 988945
A25: Outros | C25: 4868 | D25: 5560 | E25: 6273 | F25: 6273 | G25: 36 | H25: 36
A26: Total do ativo não circulante | C26: =SUM(C19,C20,C21,C22,C23,C24,C25) -> 788335 | D26: =SUM(D19,D20,D21,D22,D23,D24,D25) -> 874035 | E26: =SUM(E19,E20,E21,E22,E23,E24,E25) -> 1127794 | F26: =SUM(F19,F20,F21,F22,F23,F24,F25) -> 1303191 | G26: =SUM(G19,G20,G21,G22,G23,G24,G25) -> 1379162 | H26: =SUM(H19,H20,H21,H22,H23,H24,H25) -> 1561908
A28: TOTAL DO ATIVO | C28: =C14+C16+C26 -> 1131893 | D28: =D14+D16+D26 -> 1389902 | E28: =E14+E16+E26 -> 1531041 | F28: =F14+F16+F26 -> 1731911 | G28: =G14+G16+G26 -> 1992348 | H28: =H14+H16+H26 -> 2221103
A30: PASSIVO
A31: Circulante
A32: Fornecedores e outras obrigações | B32: 9 | C32: 179934 | D32: 197384 | E32: 282783 | F32: 285231 | G32: 334711 | H32: 345941
A33: Empréstimos | C33: 35948
A34: Impostos e contribuições sociais | B34: 10 | C34: 48246 | D34: 32546 | E34: 44200 | F34: 47291 | G34: 73832 | H34: 85429
A35: Obrigações trabalhistas e sociais | B35: 11 | C35: 33347 | D35: 24580 | E35: 40814 | F35: 41620 | G35: 62092 | H35: 63986
A36: Adiantamentos recebidos | B36: 12 | C36: 94692 | D36: 120772 | E36: 136988 | F36: 150728 | G36: 121697 | H36: 142752
A37: Outorga concessão de uso de bem público (CP) | B37: 7.1 | F37: 4931 | H37: 8480
A38: Total do passivo circulante | C38: =SUM(C32,C33,C34,C35,C36,C37) -> 392167 | D38: =SUM(D32,D33,D34,D35,D36,D37) -> 375282 | E38: =SUM(E32,E33,E34,E35,E36,E37) -> 504785 | F38: =SUM(F32,F33,F34,F35,F36,F37) -> 529801 | G38: =SUM(G32,G33,G34,G35,G36,G37) -> 592332 | H38: =SUM(H32,H33,H34,H35,H36,H37) -> 646588
A40: Não circulante
A41: Fornecedores e outras obrigações | B41: 9 | C41: 86369 | D41: 116942 | E41: 160530 | F41: 160530 | G41: 226369 | H41: 226369
A42: Empréstimos
A43: Impostos e contribuições sociais | B43: 10 | C43: 196588 | D43: 155543 | E43: 151799 | F43: 151799 | G43: 147301 | H43: 147301
A44: Provisão para contingências | B44: 13 | C44: 100247 | D44: 88044 | E44: 95467 | F44: 95467 | G44: 72221 | H44: 72221
A45: Adiantamentos recebidos LP | C45: 21976
A46: Outorga concessão de uso de bem público (LP) | B46: 7.1 | F46: 174561 | H46: 171058
A47: Total do passivo não circulante | C47: =SUM(C41,C42,C43,C44,C45,C46) -> 405180 | D47: =SUM(D41,D42,D43,D44,D45,D46) -> 360529 | E47: =SUM(E41,E42,E43,E44,E45,E46) -> 407796 | F47: =SUM(F41,F42,F43,F44,F45,F46) -> 582357 | G47: =SUM(G41,G42,G43,G44,G45,G46) -> 445891 | H47: =SUM(H41,H42,H43,H44,H45,H46) -> 616949
A49: TOTAL DO PASSIVO | C49: =C38+C47 -> 797347 | D49: =D38+D47 -> 735811 | E49: =E38+E47 -> 912581 | F49: =F38+F47 -> 1112158 | G49: =G38+G47 -> 1038223 | H49: =H38+H47 -> 1263537
A51: PATRIMÔNIO LÍQUIDO
A52: Ajuste de avaliação patrimonial | B52: 14 | C52: 201332 | D52: 192981 | E52: 174336 | F52: 174336 | G52: 145127 | H52: 145127
A53: Superávits acumulados | B53: 14 | C53: 133214 | D53: 461110 | E53: 444124 | F53: 444124 | G53: 808998 | H53: 808998
A54: Subtotal patrimônio do controlador | C54: =SUM(C52,C53) -> 334546 | D54: =SUM(D52,D53) -> 654091 | E54: =SUM(E52,E53) -> 618460 | F54: =SUM(F52,F53) -> 618460 | G54: =SUM(G52,G53) -> 954125 | H54: =SUM(H52,H53) -> 954125
A55: Participação na investida do sócio não-controlador | B55: 5 | F55: 1293 | H55: 3441
A56: Total do patrimônio líquido | C56: =C54+C55 -> 334546 | D56: =D54+D55 -> 654091 | E56: =E54+E55 -> 618460 | F56: =F54+F55 -> 619753 | G56: =G54+G55 -> 954125 | H56: =H54+H55 -> 957566
A58: TOTAL DO PASSIVO + PATRIMÔNIO LÍQUIDO | C58: =C49+C56 -> 1131893 | D58: =D49+D56 -> 1389902 | E58: =E49+E56 -> 1531041 | F58: =F49+F56 -> 1731911 | G58: =G49+G56 -> 1992348 | H58: =H49+H56 -> 2221103
A60: CONFERÊNCIA: Ativo − (Passivo + PL) | C60: =C28-C58 -> 0 | D60: =D28-D58 -> 0 | E60: =E28-E58 -> 0 | F60: =F28-F58 -> 0 | G60: =G28-G58 -> 0 | H60: =H28-H58 -> 0
A62: Notas críticas:
A63: • Para 2022 e 2023 não havia ainda Fla-Flu Serviços S.A. (criada 30/08/2024) — só coluna Controladora.
A64: • 2022 e 2023: C/R agrupa 'Contas a receber operacionais' + 'C/R transferência jogadores CP' (apresentado separado no BP original).
A65: • 2022 e 2023: 'Outros' do circulante e não circulante são residuais — itens pulverizados não destacados pelo clube.
A66: • 2022: Depósitos judiciais estimado em R$ 53.076 a partir do comparativo do BP 2023.
A67: • 2024 e 2025: BP segue apresentação reorganizada onde Fornecedores e outras obrigações já agrupa Fornecedores + C/P transferência jogadores.
A68: • Hilton Rio By Yoo: em 2022 estava em 'Propriedades para investimento'. Reclassificado parcialmente para 'Disponível para venda' a partir de 2023.
A69: • Investimento Fla-Flu aparece apenas na Controladora — no Consolidado é eliminado por equivalência patrimonial.
A70: • Outorga concessão Maracanã: passivo da Fla-Flu, aparece apenas no Consolidado.
A71: • Instrumentos financeiros (forwards USD/EUR): estreia em 2025 — primeiro hedge cambial do clube.
A72: • Conferência Ativo − (Passivo + PL) deve ser zero em todas as colunas.

Sheet DRE
A1: Clube de Regatas do Flamengo — Demonstração do Resultado do Exercício
A2: Valores em R$ milhares — 4 exercícios consecutivos | 2022 e 2023 reapresentados sob ITG 2003 R2
A4: Linha | B4: Nota | C4: 2022 reapr. | D4: 2023 reapr. | E4: 2024 Cont. | F4: 2024 Consol. | G4: 2025 Cont. | H4: 2025 Consol.
A6: Receita operacional líquida | B6: 15 | C6: 979078 | D6: 1012380 | E6: 1142151 | F6: 1158862 | G6: 1393755 | H6: 1499741
A8: RESULTADO BRUTO
A9: Custo das atividades sociais e esportivas | B9: 16 | C9: -761192 | D9: -853762 | E9: -982446 | F9: -988412 | G9: -1171697 | H9: -1194220
A10: Resultado bruto | C10: =C6+C9 -> 217886 | D10: =D6+D9 -> 158618 | E10: =E6+E9 -> 159705 | F10: =F6+F9 -> 170450 | G10: =G6+G9 -> 222058 | H10: =H6+H9 -> 305521
A11: Margem bruta (%) | C11: =IFERROR(C10/C6,0) -> 0.22254202 | D11: =IFERROR(D10/D6,0) -> 0.15667832 | E11: =IFERROR(E10/E6,0) -> 0.13982827 | F11: =IFERROR(F10/F6,0) -> 0.14708395 | G11: =IFERROR(G10/G6,0) -> 0.15932355 | H11: =IFERROR(H10/H6,0) -> 0.20371584
A13: DESPESAS OPERACIONAIS
A14: Despesas administrativas | B14: 17 | C14: -78698 | D14: -74523 | E14: -113121 | F14: -118490 | G14: -121492 | H14: -142285
A15: Despesas comerciais | B15: 18 | C15: -31171 | D15: -31871 | E15: -37759 | F15: -37759 | G15: -37763 | H15: -39610
A16: Outras receitas (despesas) operacionais líquidas | B16: 19 | C16: 48659 | D16: 239475 | E16: 39389 | F16: 31930 | G16: 236718 | H16: 227260
A17: Resultado de equivalência patrimonial (Fla-Flu) | B17: 5 | E17: -3465 | G17: 13939
A18: Resultado operacional antes do resultado financeiro | C18: =C10+C14+C15+C16+C17 -> 156676 | D18: =D10+D14+D15+D16+D17 -> 291699 | E18: =E10+E14+E15+E16+E17 -> 44749 | F18: =F10+F14+F15+F16+F17 -> 46131 | G18: =G10+G14+G15+G16+G17 -> 313460 | H18: =H10+H14+H15+H16+H17 -> 350886
A19: Margem operacional (%) | C19: =IFERROR(C18/C6,0) -> 0.16002402 | D19: =IFERROR(D18/D6,0) -> 0.28813193 | E19: =IFERROR(E18/E6,0) -> 0.039179583 | F19: =IFERROR(F18/F6,0) -> 0.039807156 | G19: =IFERROR(G18/G6,0) -> 0.22490323 | H19: =IFERROR(H18/H6,0) -> 0.2339644
A21: RESULTADO FINANCEIRO
A22: Despesas financeiras | B22: 20 | C22: -34274 | D22: -30657 | E22: -59474 | F22: -61556 | G22: -28534 | H22: -46501
A23: Receitas financeiras | B23: 20 | C23: 13288 | D23: 58503 | E23: 13991 | F23: 15370 | G23: 50739 | H23: 53492
A24: Resultado financeiro líquido | C24: =C22+C23 -> -20986 | D24: =D22+D23 -> 27846 | E24: =E22+E23 -> -45483 | F24: =F22+F23 -> -46186 | G24: =G22+G23 -> 22205 | H24: =H22+H23 -> 6991
A26: Resultado antes do IR/CSLL | C26: =C18+C24 -> 135690 | D26: =D18+D24 -> 319545 | E26: =E18+E24 -> -734 | F26: =F18+F24 -> -55 | G26: =G18+G24 -> 335665 | H26: =H18+H24 -> 357877
A27: Imposto de renda e contribuição social | B27: 10 | F27: -2546 | H27: -14706
A28: SUPERÁVIT / (DÉFICIT) DO EXERCÍCIO | C28: =C26+C27 -> 135690 | D28: =D26+D27 -> 319545 | E28: =E26+E27 -> -734 | F28: =F26+F27 -> -2601 | G28: =G26+G27 -> 335665 | H28: =H26+H27 -> 343171
A29: Margem líquida (%) | C29: =IFERROR(C28/C6,0) -> 0.13858957 | D29: =IFERROR(D28/D6,0) -> 0.31563741 | E29: =IFERROR(E28/E6,0) -> -0.00064264708 | F29: =IFERROR(F28/F6,0) -> -0.0022444433 | G29: =IFERROR(G28/G6,0) -> 0.24083501 | H29: =IFERROR(H28/H6,0) -> 0.22882018
A31: Notas críticas:
A32: • 2023 reapresentado conforme NE 2.14 do balanço 2024 — segregação de vendas de atletas da Receita Operacional para 'Outras receitas operacionais' (impacto na Receita: -R$ 303.493 / no Custo: +R$ 82.322 / em Outras: +R$ 221.171).
A33: • 2022 reapresentado retroativamente por consistência metodológica — receita de transferências de atletas (R$ 133.351, NE original 2022) removida da Receita e custos diretos relacionados (R$ 66.346 = baixa direitos profissionais 41.580 + gastos com negociações 18.366 + repasse direitos econômicos 6.400) realocados de Custo para Outras. Superávit final inalterado.
A34: • 2022: 'baixa direitos econômicos formação' (R$ 18.411) NÃO foi reclassificada — refere-se a amortização de atletas formados, não a custo direto de venda.
A35: • Equivalência patrimonial só aparece na Controladora — no Consolidado a Fla-Flu é integrada linha por linha.
A36: • IR/CSLL: Flamengo (associação) é isento. Linha aparece apenas no Consolidado a partir de 2024, refletindo a Fla-Flu Serviços S.A. tributada por lucro presumido.
A37: • Em 2025, Outras receitas (despesas) operacionais líquidas contém R$ 267.360 (líquido) de movimentação de atletas — Mundial e Intercontinental NÃO entram aqui (vão em Participação/exposição na Receita).
A38: • Margem bruta de 2025 (16% Cont / 20% Consol) está deprimida pela linha de Custos — a margem efetiva do clube vê-se melhor no resultado operacional antes do financeiro.
A39: • 2022 e 2023: sem Fla-Flu, sem Consolidado. Linhas Consolidado aparecem zeradas/vazias.
A42: Reconciliação da reapresentação de 2022 (metodologia)
A43: Linha | C43: Original 2022 | E43: Ajuste | G43: Reapresentado 2022
A44: Receita operacional líquida | C44: 1112429 | E44: -133351 | G44: 979078
A45: Custo das atividades | C45: -827538 | E45: 66346 | G45: -761192
A46: Resultado bruto | C46: 284891 | E46: -67005 | G46: 217886
A47: Outras receitas (despesas) op. líq. | C47: -18346 | E47: 67005 | G47: 48659
A48: Resultado op. antes do financeiro | C48: 156676 | E48: 0 | G48: 156676
A49: Superávit do exercício | C49: 135690 | E49: 0 | G49: 135690

Sheet Receita Detalhada
A1: Clube de Regatas do Flamengo — Receita Operacional Detalhada
A2: Decomposição por categoria conforme NE 15 — Receita BRUTA (antes de deduções) | Sem transferências de atletas
A4: Linha | B4: Nota | C4: 2022 | D4: 2023 | E4: 2024 Cont. | F4: 2024 Consol. | G4: 2025 Cont. | H4: 2025 Consol.
A6: BROADCAST / MÍDIA
A7: Direitos de transmissão fixos | B7: 15 | C7: 57637 | D7: 149870 | E7: 141948 | F7: 141948 | G7: 203368 | H7: 203368
A8: Participação, exposição, performance (linha-chave do eixo) | B8: 15 | C8: 264739 | D8: 96992 | E8: 132374 | F8: 132374 | G8: 378797 | H8: 378797
A9: Mídias digitais on demand | B9: 15 | C9: 173210 | D9: 178534 | E9: 179221 | F9: 179221 | G9: 29388 | H9: 29388
A10: Subtotal Broadcast/Mídia | C10: =SUM(C7,C8,C9) -> 495586 | D10: =SUM(D7,D8,D9) -> 425396 | E10: =SUM(E7,E8,E9) -> 453543 | F10: =SUM(F7,F8,F9) -> 453543 | G10: =SUM(G7,G8,G9) -> 611553 | H10: =SUM(H7,H8,H9) -> 611553
A12: COMERCIAL
A13: Licenciamento e royalties | B13: 15 | C13: 88063 | D13: 96954 | E13: 97720 | F13: 97720 | G13: 131044 | H13: 131044
A14: Patrocínio e publicidade | B14: 15 | C14: 149803 | D14: 226039 | E14: 320022 | F14: 320022 | G14: 401401 | H14: 401401
A15: Subtotal Comercial | C15: =SUM(C13,C14) -> 237866 | D15: =SUM(D13,D14) -> 322993 | E15: =SUM(E13,E14) -> 417742 | F15: =SUM(F13,F14) -> 417742 | G15: =SUM(G13,G14) -> 532445 | H15: =SUM(H13,H14) -> 532445
A17: OPERAÇÕES DE JOGOS (MATCHDAY)
A18: Bilheteria | B18: 15 | C18: 101231 | D18: 123267 | E18: 118062 | F18: 118062 | G18: 142490 | H18: 142490
A19: Estádio (Controladora) | B19: 15 | C19: 25561 | D19: 46143 | E19: 47711 | F19: 47711 | G19: 11398 | H19: 11398
A20: Estádio Fla-Flu (camarotes/locação) — só Consolidado | B20: 15 | F20: 16711 | H20: 80400
A21: Visitação Maracanã (Tour) — só Consolidado | B21: 15 | H21: 26500
A22: Sócio Torcedor | B22: 15 | C22: 72483 | D22: 90861 | E22: 77766 | F22: 77766 | G22: 87699 | H22: 87699
A23: Subtotal Matchday | C23: =SUM(C18,C19,C20,C21,C22) -> 199275 | D23: =SUM(D18,D19,D20,D21,D22) -> 260271 | E23: =SUM(E18,E19,E20,E21,E22) -> 243539 | F23: =SUM(F18,F19,F20,F21,F22) -> 260250 | G23: =SUM(G18,G19,G20,G21,G22) -> 241587 | H23: =SUM(H18,H19,H20,H21,H22) -> 348487
A25: DIVERSOS
A26: Diversos (inclui clube social e amadores) | B26: 15 | C26: 110656 | D26: 61670 | E26: 95505 | F26: 95505 | G26: 68714 | H26: 78214
A27: Subtotal Diversos | C27: =SUM(C26) -> 110656 | D27: =SUM(D26) -> 61670 | E27: =SUM(E26) -> 95505 | F27: =SUM(F26) -> 95505 | G27: =SUM(G26) -> 68714 | H27: =SUM(H26) -> 78214
A29: RECEITA BRUTA RECORRENTE TOTAL (sem atletas) | C29: =C10+C15+C23+C27 -> 1043383 | D29: =D10+D15+D23+D27 -> 1070330 | E29: =E10+E15+E23+E27 -> 1210329 | F29: =F10+F15+F23+F27 -> 1227040 | G29: =G10+G15+G23+G27 -> 1454299 | H29: =H10+H15+H23+H27 -> 1570699
A31: TRANSFERÊNCIA DE ATLETAS — só 2022 e 2023 dentro da Receita | 2024-2025 vão em 'Outras Receitas Op.'
A32: Direitos federativos | B32: 15 | C32: 119111 | D32: 294379
A33: Mecanismo de solidariedade | B33: 15 | C33: 14240 | D33: 9114
A34: Subtotal Transferência de Atletas (apresentação ORIGINAL) | C34: =SUM(C32,C33) -> 133351 | D34: =SUM(D32,D33) -> 303493 | E34: =SUM(E32,E33) -> 0 | F34: =SUM(F32,F33) -> 0 | G34: =SUM(G32,G33) -> 0 | H34: =SUM(H32,H33) -> 0
A35: (Para 2024 e 2025 a receita de transferência de atletas está em 'Outras receitas operacionais' — ver aba DRE linha 16)
A37: RECEITA BRUTA TOTAL — informativa (com atletas em 2022-2023, apresentação original) | C37: =C29+C34 -> 1176734 | D37: =D29+D34 -> 1373823 | E37: =E29+E34 -> 1210329 | F37: =F29+F34 -> 1227040 | G37: =G29+G34 -> 1454299 | H37: =H29+H34 -> 1570699
A39: DEDUÇÕES E RECEITA LÍQUIDA
A40: (-) Deduções (PIS folha 1% / INSS receita 5% / outros) — sobre Receita Bruta Recorrente | B40: 2.8 | C40: =DRE!C6-C29 -> -64305 | D40: =DRE!D6-D29 -> -57950 | E40: =DRE!E6-E29 -> -68178 | F40: =DRE!F6-F29 -> -68178 | G40: =DRE!G6-G29 -> -60544 | H40: =DRE!H6-H29 -> -70958
A42: RECEITA OPERACIONAL LÍQUIDA (= DRE!linha 6) | C42: =DRE!C6 -> 979078 | D42: =DRE!D6 -> 1012380 | E42: =DRE!E6 -> 1142151 | F42: =DRE!F6 -> 1158862 | G42: =DRE!G6 -> 1393755 | H42: =DRE!H6 -> 1499741
A45: DECOMPOSIÇÃO ANALÍTICA — "Participação, exposição, performance" (premissas ajustáveis)
A46: Premissas em AMARELO são editáveis — heurísticas iniciais baseadas em premiações divulgadas
A47: Cotas fixas Libertadores (fase de grupos) | C47: 16400 | D47: 16400 | E47: 16400 | F47: 16400 | G47: 16400 | H47: 16400
A48: Premiações nacionais ex-Brasileirão (Supercopa + Copa Brasil + Carioca) | C48: 20000 | D48: 15000 | E48: 8000 | F48: 8000 | G48: 22300 | H48: 22300
A49: Performance Libertadores (vitórias + oitavas/quartas/semi/título) | C49: 120000 | D49: 14000 | E49: 14000 | F49: 14000 | G49: 163600 | H49: 163600
A50: Prêmio FIFA Mundial de Clubes (jun-jul 2025) — não-recorrente | C50: 10000 | G50: 152600 | H50: 152600
A51: Prêmio FIFA Intercontinental (dez 2025) — não-recorrente | G51: 21600 | H51: 21600
A52: Outras participações / exposição (resíduo) | C52: 98339 | D52: 51592 | E52: 93974 | F52: 93974 | G52: 2297 | H52: 2297
A53: Soma da decomposição (deve bater com linha 8) | C53: =SUM(C47,C48,C49,C50,C51,C52) -> 264739 | D53: =SUM(D47,D48,D49,D50,D51,D52) -> 96992 | E53: =SUM(E47,E48,E49,E50,E51,E52) -> 132374 | F53: =SUM(F47,F48,F49,F50,F51,F52) -> 132374 | G53: =SUM(G47,G48,G49,G50,G51,G52) -> 378797 | H53: =SUM(H47,H48,H49,H50,H51,H52) -> 378797
A54: VERIFICAÇÃO: Soma da decomposição − Linha 8 (deve ser zero) | C54: =C53-C8 -> 0 | D54: =D53-D8 -> 0 | E54: =E53-E8 -> 0 | F54: =F53-F8 -> 0 | G54: =G53-G8 -> 0 | H54: =H53-H8 -> 0
A56: EFEITO FIFA 2025 (Mundial + Intercontinental) — para a aba Operacional Puro | C56: =C50+C51 -> 10000 | D56: =D50+D51 -> 0 | E56: =E50+E51 -> 0 | F56: =F50+F51 -> 0 | G56: =G50+G51 -> 174200 | H56: =H50+H51 -> 174200
A58: Notas críticas:
A59: • Detalhamento da NE 15 do balanço 2025 (e NE 17 do balanço 2024 para os comparativos 2023 e 2024) — apresentação reorganizada após 2022.
A60: • 2022 reorganizado para formato consistente: 'Patrocínio' foi extraído de 'Mídia' (apresentação original) para 'Comercial'; 'Licenciamento' foi extraído de 'Mídias digitais' para 'Comercial'. Total inalterado.
A61: • 2023 reapresentado: a NE 17 do balanço 2024 já trouxe os comparativos reorganizados (vendas de atletas fora da Receita).
A62: • Linha 8 (Participação, exposição, performance) é a CENTRAL para o eixo do post. Triplicou em 2025 vs 2024 (+186%, +R$ 246 mi).
A63: • Estádio Controladora caiu -76% em 2025 vs 2024 (R$ 47,7 → R$ 11,4 mi) por migração da gestão Maracanã para a Fla-Flu — o impacto se compensa na linha 20 (Estádio Fla-Flu).
A64: • Mídias digitais on demand caiu -84% em 2025 — reclassificação contábil (foi para 'Transmissão fixos' e 'Participação'), NÃO queda real.
A65: • Estádio Fla-Flu 2024 Consol estimado em R$ 16,7 mi (operação parcial set-dez/2024) — premissa, ajustável.
A66: • Decomposição da linha-chave (linhas 47-52): premissas iniciais baseadas em divulgações públicas. Vinicius ajusta a partir de seus conhecimentos sobre premiações.
A67: • Prêmio FIFA Mundial estimado em R$ 140 mi (USD ~28M considerando classificação à fase de grupos + saída nas oitavas — Flamengo eliminado pelo Bayern). Intercontinental estimado em R$ 28,8 mi (residual).
A68: • Soma deve bater EXATAMENTE com Linha 8 — célula de verificação na linha 54.
A69: • Linha 56 isola o efeito FIFA não-recorrente de 2025 (Mundial + Intercontinental) — alimenta a aba Operacional Puro para calcular EBITDA Recorrente Puro.

Sheet DFC
A1: Clube de Regatas do Flamengo — Demonstração dos Fluxos de Caixa
A2: Método indireto | R$ milhares | Caixa LIVRE (sem restrito) | 2022 sem detalhe DFC
A4: Linha | B4: Nota | C4: 2022 | D4: 2023 | E4: 2024 Cont. | F4: 2024 Consol. | G4: 2025 Cont. | H4: 2025 Consol.
A6: ATIVIDADES OPERACIONAIS
A7: Superávit/(Déficit) do exercício | C7: =DRE!C28 -> 135690 | D7: =DRE!D28 -> 319545 | E7: =DRE!E28 -> -734 | F7: =DRE!F28 -> -2601 | G7: =DRE!G28 -> 335665 | H7: =DRE!H28 -> 343171
A9: Ajustes para conciliação ao caixa operacional:
A10: Amortização de direitos sobre atletas | B10: 7 | C10: 121656 | D10: 175729 | E10: 213621 | F10: 213621 | G10: 243716 | H10: 243716
A11: Depreciação de imobilizado e outras amortizações | E11: 10651 | F11: 11394 | G11: 12070 | H11: 12625
A12: Baixa de custos com aquisição de direitos federativos (NOVO 2025) | G12: 197912 | H12: 197912
A13: Amortização outorga concessão Maracanã (só Consolidado) | H13: 9434
A14: (-) Resultado de equivalência patrimonial Fla-Flu (só Cont) | B14: 5 | E14: 3465 | G14: -13939
A15: (-) Ajuste a valor presente instrumentos financeiros (NOVO 2025) | G15: -3086 | H15: -3086
A16: Outros ajustes (juros parcelamentos, var. cambial não-caixa, contingências, etc.) | E16: 31515 | F16: 31544 | G16: 21088 | H16: 33543
A17: Subtotal ajustes | C17: =SUM(C10:C16) -> 121656 | D17: =SUM(D10:D16) -> 175729 | E17: =SUM(E10:E16) -> 259252 | F17: =SUM(F10:F16) -> 256559 | G17: =SUM(G10:G16) -> 457761 | H17: =SUM(H10:H16) -> 494144
A19: Variações em ativos e passivos operacionais:
A20: (Aumento) redução em contas a receber (incl. C/R jogadores) | B20: 4 | E20: -5177 | F20: -8000 | G20: -234803 | H20: -226747
A21: Aumento (redução) em fornecedores e C/P jogadores | B21: 9 | E21: 135051 | F21: 137000 | G21: 117767 | H21: 126549
A22: Aumento (redução) em adiantamentos recebidos | B22: 12 | E22: 15946 | F22: 29956 | G22: -15291 | H22: -7976
A23: Outras variações líquidas (residual: depós. judiciais, contingências, AVP, etc.) | E23: 4177 | F23: 8317 | G23: -61836 | H23: -69258
A24: Outorga concessão em capital de giro (só Consolidado, NOVO 2025) | H24: 20107
A25: Subtotal variações | C25: =SUM(C20:C24) -> 0 | D25: =SUM(D20:D24) -> 0 | E25: =SUM(E20:E24) -> 149997 | F25: =SUM(F20:F24) -> 167273 | G25: =SUM(G20:G24) -> -194163 | H25: =SUM(H20:H24) -> -157325
A27: CAIXA LÍQUIDO DE ATIVIDADES OPERACIONAIS | C27: =C7+C17+C25 -> 257346 | D27: 351089 | E27: =E7+E17+E25 -> 408515 | F27: =F7+F17+F25 -> 421231 | G27: =G7+G17+G25 -> 599263 | H27: =H7+H17+H25 -> 679990
A29: ATIVIDADES DE INVESTIMENTO
A30: Pagamento de compra de direitos sobre jogadores | B30: 7 | E30: -382368 | F30: -382368 | G30: -507575 | H30: -507575
A31: Compras de imobilizado | B31: 8 | E31: -181376 | F31: -181833 | G31: -25212 | H31: -38458
A32: Investimento em aquisição de bem público (só Consolidado 2025) | H32: -20458
A33: Investimento na Fla-Flu (só Controladora) | B33: 5 | E33: -5866
A34: Alienação Hilton Rio By Yoo | B34: 6 | E34: 21027 | F34: 21027 | G34: 34167 | H34: 34167
A35: Outras atividades de investimento | E35: -16064 | F35: -16064 | G35: -18501 | H35: -25654
A36: CAIXA APLICADO EM ATIVIDADES DE INVESTIMENTO | C36: =SUM(C30:C35) -> 0 | D36: -312929 | E36: =SUM(E30:E35) -> -564647 | F36: =SUM(F30:F35) -> -559238 | G36: =SUM(G30:G35) -> -517121 | H36: =SUM(H30:H35) -> -557978
A38: FREE CASH FLOW (Op + Inv) — métrica analítica | C38: =C27+C36 -> 257346 | D38: =D27+D36 -> 38160 | E38: =E27+E36 -> -156132 | F38: =F27+F36 -> -138007 | G38: =G27+G36 -> 82142 | H38: =H27+H36 -> 122012
A40: ATIVIDADES DE FINANCIAMENTO
A41: Capital integralizado / outras movimentações de financiamento (residual) | B41: 5 | F41: 3159 | H41: 12038
A42: Pagamento de empréstimos | D42: -31533
A43: Pagamento de impostos parcelados (PROFUT/PERSE) | B43: 10 | D43: -9027 | E43: -7798 | F43: -7798 | G43: -8758 | H43: -8758
A44: Pagamento de outorga (concessão Maracanã, só Consolidado) | B44: 7.1 | H44: -20061
A45: Dividendos pagos ao não-controlador (Fla-Flu → Fluminense) | B45: 5 | H45: -5358
A46: CAIXA APLICADO EM ATIVIDADES DE FINANCIAMENTO | C46: =SUM(C41:C45) -> 0 | D46: =SUM(D41:D45) -> -40560 | E46: =SUM(E41:E45) -> -7798 | F46: =SUM(F41:F45) -> -4639 | G46: =SUM(G41:G45) -> -8758 | H46: =SUM(H41:H45) -> -22139
A48: VARIAÇÃO DO CAIXA NO EXERCÍCIO
A49: VARIAÇÃO LÍQUIDA DO CAIXA | C49: =C27+C36+C46 -> 257346 | D49: =D27+D36+D46 -> -2400 | E49: =E27+E36+E46 -> -163930 | F49: =F27+F36+F46 -> -142646 | G49: =G27+G36+G46 -> 73384 | H49: =H27+H36+H46 -> 99873
A51: Caixa LIVRE no início do exercício | C51: 127182 | D51: 236887 | E51: 234487 | F51: 234487 | G51: 70557 | H51: 91841
A52: Caixa LIVRE no fim do exercício (= BP linha 7) | C52: =BP!C7 -> 236887 | D52: =BP!D7 -> 234487 | E52: =BP!E7 -> 70557 | F52: =BP!F7 -> 91841 | G52: =BP!G7 -> 143941 | H52: =BP!H7 -> 191714
A53: VERIFICAÇÃO: Variação líquida − (Final − Inicial) = 0 | C53: =C49-(C52-C51) -> 147641 | D53: =D49-(D52-D51) -> 0 | E53: =E49-(E52-E51) -> 0 | F53: =F49-(F52-F51) -> 0 | G53: =G49-(G52-G51) -> 0 | H53: =H49-(H52-H51) -> 0
A55: RECONCILIAÇÃO ANALÍTICA — Capex de atletas: caixa vs contábil
A56: Capex CONTÁBIL de atletas (adições intangível NE 7) | B56: 7 | E56: 414808 | F56: 414808 | G56: 635605 | H56: 635605
A57: (-) Pagamento CAIXA de jogadores (DFC investimento) | C57: =-C30 -> 0 | D57: =-D30 -> 0 | E57: =-E30 -> 382368 | F57: =-F30 -> 382368 | G57: =-G30 -> 507575 | H57: =-H30 -> 507575
A58: Financiamento via C/P jogadores (clubes vendedores) | C58: =C56-C57 -> 0 | D58: =D56-D57 -> 0 | E58: =E56-E57 -> 32440 | F58: =F56-F57 -> 32440 | G58: =G56-G57 -> 128030 | H58: =H56-H57 -> 128030
A60: Notas críticas:
A61: • 2022: DFC não detalhada no handoff — todas as linhas e totais ficaram em branco. Vinicius preenche com base no PDF auditado se quiser detalhe completo.
A62: • 2023: totais Op/Inv/Fin reportados como hardcode (Op 351.089 / Inv -312.929 / Fin -40.560), sem detalhamento linha-a-linha.
A63: • Linha 23 ('Outras variações líquidas') é RESIDUAL — absorve variações em depósitos judiciais, contingências, despesas antecipadas, estoques, ajustes de AVP, var. cambial não-caixa e outros itens não detalhados linha-a-linha. Calibrada para fechar com o caixa operacional reportado.
A64: • Linha 12 NOVA em 2025: 'Baixa de custos com aquisição de direitos federativos' = R$ 197.912 = soma das baixas em NE 7 (direitos federativos 196.708 + atletas profissionais formados 1.204).
A65: • Linha 13 NOVA em 2025 (consol): amortização da outorga Maracanã (R$ 9.434), conforme NE 7.1.
A66: • Linha 15 NOVA em 2025: AVP dos forwards cambiais (sinal invertido para o caixa, pois já está no resultado).
A67: • Linha 32 NOVA em 2025 (consol): Investimento em aquisição de bem público (R$ 20.458) — segunda parcela de outorga Maracanã capitalizada.
A68: • Linha 24 NOVA em 2025 (consol): 'Outorga concessão em capital de giro' (R$ 20.107) — recebimento prévio relacionado à concessão.
A69: • Linha 45 (NOVO 2025): Dividendos pagos pela Fla-Flu ao Fluminense (R$ 5.358). Para o Flamengo, o dividendo equivalente (R$ 9.951) NÃO transitou em caixa em 2025 — está em C/R no balanço.
A70: • Capex CONTÁBIL de atletas em 2025: R$ 635.605 (linha 56). Capex CAIXA: R$ 507.575 (linha 57). Diferença R$ 128.030 = financiamento via fornecedores (linha 58).
A71: • Free Cash Flow virou positivo em 2025 (Cont +R$ 82.142 / Consol +R$ 122.012) vs negativo em 2024 (Cont -R$ 156.132 / Consol -R$ 138.007). Swing de +R$ 238 mi na controladora.
... A73: • Linha 41 (Capital integralizado / outras mov. financiamento) é RESIDUAL no 2025 Consol — captura R$ 12.038 de captações não detalhadas no handoff (provavelmente integralização adicional do Fluminense para completar capital social Fla-Flu, ou variações em passivos de financiamento da Fla-Flu).

Sheet Operacional Puro
A1: Clube de Regatas do Flamengo — Operacional Puro: EBITDA Recorrente Puro
A2: Reconciliação do EBITDA reportado para o EBITDA limpo de eventos não-recorrentes | R$ milhares nominais
A4: Linha | B4: Nota | C4: 2022 | D4: 2023 | E4: 2024 Cont. | F4: 2024 Consol. | G4: 2025 Cont. | H4: 2025 Consol.
A6: RECONSTRUÇÃO DO EBITDA REPORTADO
A7: Resultado operacional antes do financeiro (= DRE!18) | C7: =DRE!C18 -> 156676 | D7: =DRE!D18 -> 291699 | E7: =DRE!E18 -> 44749 | F7: =DRE!F18 -> 46131 | G7: =DRE!G18 -> 313460 | H7: =DRE!H18 -> 350886
A8: (+) Amortização de direitos sobre atletas (= DFC!10) | C8: =DFC!C10 -> 121656 | D8: =DFC!D10 -> 175729 | E8: =DFC!E10 -> 213621 | F8: =DFC!F10 -> 213621 | G8: =DFC!G10 -> 243716 | H8: =DFC!H10 -> 243716
A9: (+) Depreciação imobilizado e outras amortizações (= DFC!11) | C9: 8000 | D9: 7731 | E9: =DFC!E11 -> 10651 | F9: =DFC!F11 -> 11394 | G9: =DFC!G11 -> 12070 | H9: =DFC!H11 -> 12625
A11: EBITDA REPORTADO | C11: =C7+C8+C9 -> 286332 | D11: =D7+D8+D9 -> 475159 | E11: =E7+E8+E9 -> 269021 | F11: =F7+F8+F9 -> 271146 | G11: =G7+G8+G9 -> 569246 | H11: =H7+H8+H9 -> 607227
A13: AJUSTES NÃO-RECORRENTES (a subtrair do EBITDA reportado)
A14: (-) Ganho líquido com venda de atletas | B14: 19 | C14: 67005 | D14: 221171 | E14: 47233 | F14: 47233 | G14: 267360 | H14: 267360
A15: (-) Ganho na venda de unidades Hilton Rio By Yoo | B15: 6 | C15: 0 | D15: 0 | E15: 8158 | F15: 8158 | G15: 7010 | H15: 7010
A16: (-) Resultado de equivalência patrimonial Fla-Flu (só Cont) | B16: 5 | E16: -3465 | G16: 13939
A17: (-) Prêmio FIFA Mundial de Clubes 2025 (não-recorrente) | B17: 15 | G17: 152600 | H17: 152600
A18: (-) Prêmio FIFA Intercontinental 2025 (não-recorrente) | B18: 15 | G18: 21600 | H18: 21600
A19: (-) Reversão líquida de contingências 2025 | B19: 13 | G19: 23246 | H19: 23246
A20: (-) Desconto PERSE em Outras receitas operacionais (2023) | B20: 21 | D20: 19440 | E20: 0 | F20: 0 | G20: 0 | H20: 0
A21: (-) Acordo BACEN líquido (reversão R$ 83 mi - pagamento R$ 25,5 mi) | C21: 57500
A22: (-) Prêmio Mundial de Clubes 2022 (formato antigo) | C22: 10000
A24: Total dos ajustes não-recorrentes | C24: =SUM(C14:C22) -> 134505 | D24: =SUM(D14:D22) -> 240611 | E24: =SUM(E14:E22) -> 51926 | F24: =SUM(F14:F22) -> 55391 | G24: =SUM(G14:G22) -> 485755 | H24: =SUM(H14:H22) -> 471816
A26: EBITDA RECORRENTE PURO | C26: =C11-C24 -> 151827 | D26: =D11-D24 -> 234548 | E26: =E11-E24 -> 217095 | F26: =F11-F24 -> 215755 | G26: =G11-G24 -> 83491 | H26: =H11-H24 -> 135411
A28: INDICADORES — Receita Recorrente e Margens
A29: Receita Operacional Líquida (= DRE!6) | C29: =DRE!C6 -> 979078 | D29: =DRE!D6 -> 1012380 | E29: =DRE!E6 -> 1142151 | F29: =DRE!F6 -> 1158862 | G29: =DRE!G6 -> 1393755 | H29: =DRE!H6 -> 1499741
A30: (-) Efeito FIFA 2025 (Mundial + Intercontinental, da Rec. Detalhada!56) | C30: ='Receita Detalhada'!C56 -> 10000 | D30: ='Receita Detalhada'!D56 -> 0 | E30: ='Receita Detalhada'!E56 -> 0 | F30: ='Receita Detalhada'!F56 -> 0 | G30: ='Receita Detalhada'!G56 -> 174200 | H30: ='Receita Detalhada'!H56 -> 174200
A31: RECEITA RECORRENTE LÍQUIDA | C31: =C29-C30 -> 969078 | D31: =D29-D30 -> 1012380 | E31: =E29-E30 -> 1142151 | F31: =F29-F30 -> 1158862 | G31: =G29-G30 -> 1219555 | H31: =H29-H30 -> 1325541
A33: Margem EBITDA Reportado / Receita Operacional Líquida | C33: =IFERROR(C11/C29,0) -> 0.29245065 | D33: =IFERROR(D11/D29,0) -> 0.46934847 | E33: =IFERROR(E11/E29,0) -> 0.23553891 | F33: =IFERROR(F11/F29,0) -> 0.23397609 | G33: =IFERROR(G11/G29,0) -> 0.40842616 | H33: =IFERROR(H11/H29,0) -> 0.40488791
A34: Margem EBITDA Recorrente Puro / Receita Recorrente Líquida | C34: =IFERROR(C26/C31,0) -> 0.1566716 | D34: =IFERROR(D26/D31,0) -> 0.2316798 | E34: =IFERROR(E26/E31,0) -> 0.19007557 | F34: =IFERROR(F26/F31,0) -> 0.18617834 | G34: =IFERROR(G26/G31,0) -> 0.068460217 | H34: =IFERROR(H26/H31,0) -> 0.10215527
A36: FOLHA AMPLIADA — Condição 1
A37: Salários, encargos e benefícios (CMV — futebol) | B37: 16 | C37: 348980 | D37: 339050 | E37: 386020 | F37: 386020 | G37: 525089 | H37: 540000
A38: Direito de imagem (CMV — futebol) | B38: 16 | C38: 89456 | D38: 124000 | E38: 138020 | F38: 138020 | G38: 171094 | H38: 171094
A40: FOLHA AMPLIADA TOTAL (salários + DI, sem amort. atletas) | C40: =C37+C38 -> 438436 | D40: =D37+D38 -> 463050 | E40: =E37+E38 -> 524040 | F40: =F37+F38 -> 524040 | G40: =G37+G38 -> 696183 | H40: =H37+H38 -> 711094
A42: Folha ampliada / Receita Operacional Líquida | C42: =IFERROR(C40/C29,0) -> 0.44780498 | D42: =IFERROR(D40/D29,0) -> 0.45738754 | E42: =IFERROR(E40/E29,0) -> 0.45881849 | F42: =IFERROR(F40/F29,0) -> 0.45220225 | G42: =IFERROR(G40/G29,0) -> 0.49950171 | H42: =IFERROR(H40/H29,0) -> 0.47414454
A43: Folha ampliada / Receita Recorrente (CONDIÇÃO 1 — limite 65%) | C43: =IFERROR(C40/C31,0) -> 0.45242591 | D43: =IFERROR(D40/D31,0) -> 0.45738754 | E43: =IFERROR(E40/E31,0) -> 0.45881849 | F43: =IFERROR(F40/F31,0) -> 0.45220225 | G43: =IFERROR(G40/G31,0) -> 0.57085002 | H43: =IFERROR(H40/H31,0) -> 0.53645568
A45: CAPEX vs VENDAS DE ATLETAS — Condição 3
A46: Capex contábil de atletas (= DFC!56) | C46: 231000 | D46: 272510 | E46: =DFC!E56 -> 414808 | F46: =DFC!F56 -> 414808 | G46: =DFC!G56 -> 635605 | H46: =DFC!H56 -> 635605
A47: Receita de venda de atletas (federativos + sol. + empréstimos) | B47: 19 | C47: 133351 | D47: 303493 | E47: 107384 | F47: 107384 | G47: 518741 | H47: 518741
A49: Capex atletas / Vendas atletas (CONDIÇÃO 3 — limite 1,0x) | C49: =IFERROR(C46/C47,0) -> 1.7322705 | D49: =IFERROR(D46/D47,0) -> 0.89791198 | E49: =IFERROR(E46/E47,0) -> 3.8628474 | F49: =IFERROR(F46/F47,0) -> 3.8628474 | G49: =IFERROR(G46/G47,0) -> 1.2252839 | H49: =IFERROR(H46/H47,0) -> 1.2252839
A51: SENSIBILIDADE 2025 — Cenário SEM Mundial+Intercontinental (eixo do post)
A52: Esta seção materializa a tese do post: o quanto da Receita Recorrente e do EBITDA Puro depende dos R$ 174.200 da FIFA 2025
A54: 2025 Cont — Cenário SEM Mundial+Intercontinental:
A55: Receita Recorrente Líquida (já sem FIFA 2025) - linha 31 | C55: =G31 -> 1219555
A56: EBITDA Recorrente Puro 2025 Cont (linha 26) | C56: =G26 -> 83491
A57: Receita Op Líquida REPORTADA 2025 Cont (linha 29) | C57: =G29 -> 1393755
A58: Diferença (efeito FIFA 2025 isolado) — linha 30 | C58: =G30 -> 174200
A60: Margem EBITDA Recorrente Puro 2025 Cont (linha 34 G): | C60: =G34 -> 0.068460217
A61: Margem EBITDA Reportado 2025 Cont (linha 33 G): | C61: =G33 -> 0.40842616
A63: Notas críticas:
A64: • EBITDA REPORTADO calculado conforme convenção da série: Resultado Operacional antes do Financeiro + Amortização atletas + Depreciação outras.
A65: • Pode haver diferença vs EBITDA reportado pelo clube nos relatórios IPCA-corrigidos: o clube parece incluir 'baixa direitos econômicos formação' como parte da amortização (~R$ 18 mi em 2022), o que aumenta o EBITDA em ~R$ 18 mi.
A66: • Linhas 7-9 puxam direto da DRE e DFC (verdes) — alterar nas abas-fonte propaga aqui.
A67: • AJUSTES NÃO-RECORRENTES isolam: vendas de atletas (todos os anos), Hilton, equivalência Fla-Flu, prêmios FIFA Mundial e Intercontinental 2025, reversão de contingências 2025, desconto PERSE 2023 (parte que entrou em Outras Op., não no financeiro), acordo BACEN 2022, prêmio Mundial 2022 (formato antigo, ~USD 2M).
A68: • Para 2022 Acordo BACEN: efeito líquido +R$ 57,5 mi = reversão de provisão R$ 83 mi - pagamento da multa R$ 25,5 mi. O pagamento já reduzia 'Outras despesas op' na DRE, então no EBITDA o efeito é positivo R$ 57,5 mi.
A69: • Eq. patrimonial Fla-Flu aparece apenas na Controladora (no Consol está integrada linha por linha).
A70: • Efeito FIFA 2025 (linha 30) é o número-chave do eixo: R$ 174.200 que potencialmente não se repete em 2026, 2027, 2028. Próximo Mundial só em 2029.
A71: • CONDIÇÃO 1 (linha 43): Folha ampliada / Receita Recorrente — limite 65%. Para 2024 e 2025, a margem está saudável (~46-48% vs limite 65%).
A72: • CONDIÇÃO 3 (linha 49): Capex / Vendas — limite 1,0x. Falhou gritantemente em 2024 (4,06x) e passou apertado em 2025 (1,23x).
A73: • Salários Consol 2025 (linha 37) estimado em R$ 540 mi (Cont R$ 525 mi + ~R$ 15 mi pessoal Fla-Flu). Handoff não desagrega, ajustar se tiver detalhe.
A74: • Sensibilidade 2025 sem FIFA (linhas 54-58): mostra a Receita Recorrente 'limpa' que serve como piso estrutural para projeções 2026-2027.
A75: • A margem EBITDA Recorrente Puro é a métrica central do eixo — captura 'o que sobraria em um ano normal'.

Sheet Indicadores
A1: Clube de Regatas do Flamengo — Indicadores
A2: Síntese consolidada das métricas-chave para o post | R$ milhares nominais
A4: Indicador | B4: Unidade | C4: 2022 | D4: 2023 | E4: 2024 Cont. | F4: 2024 Consol. | G4: 2025 Cont. | H4: 2025 Consol.
A6: SÍNTESE DAS 4 CONDIÇÕES DE COMPETITIVIDADE FINANCEIRA
A7: CONDIÇÃO 1: Folha ampliada / Receita Recorrente | B7: ≤ 65% | C7: ='Operacional Puro'!C43 -> 0.45242591 | D7: ='Operacional Puro'!D43 -> 0.45738754 | E7: ='Operacional Puro'!E43 -> 0.45881849 | F7: ='Operacional Puro'!F43 -> 0.45220225 | G7: ='Operacional Puro'!G43 -> 0.57085002 | H7: ='Operacional Puro'!H43 -> 0.53645568
A8: → Status | C8: =IF(C7=0,"-",IF(C7<=0.5,"PASSA",IF(C7<=0.65,"APERTADO","FALHA"))) -> PASSA | D8: =IF(D7=0,"-",IF(D7<=0.5,"PASSA",IF(D7<=0.65,"APERTADO","FALHA"))) -> PASSA | E8: =IF(E7=0,"-",IF(E7<=0.5,"PASSA",IF(E7<=0.65,"APERTADO","FALHA"))) -> PASSA | F8: =IF(F7=0,"-",IF(F7<=0.5,"PASSA",IF(F7<=0.65,"APERTADO","FALHA"))) -> PASSA | G8: =IF(G7=0,"-",IF(G7<=0.5,"PASSA",IF(G7<=0.65,"APERTADO","FALHA"))) -> APERTADO | H8: =IF(H7=0,"-",IF(H7<=0.5,"PASSA",IF(H7<=0.65,"APERTADO","FALHA"))) -> APERTADO
A10: CONDIÇÃO 2: Margem EBITDA Recorrente Puro | B10: ≥ 5% | C10: ='Operacional Puro'!C34 -> 0.1566716 | D10: ='Operacional Puro'!D34 -> 0.2316798 | E10: ='Operacional Puro'!E34 -> 0.19007557 | F10: ='Operacional Puro'!F34 -> 0.18617834 | G10: ='Operacional Puro'!G34 -> 0.068460217 | H10: ='Operacional Puro'!H34 -> 0.10215527
A11: → Status | C11: =IF(C10=0,"-",IF(C10>=0.1,"PASSA",IF(C10>=0.05,"APERTADO","FALHA"))) -> PASSA | D11: =IF(D10=0,"-",IF(D10>=0.1,"PASSA",IF(D10>=0.05,"APERTADO","FALHA"))) -> PASSA | E11: =IF(E10=0,"-",IF(E10>=0.1,"PASSA",IF(E10>=0.05,"APERTADO","FALHA"))) -> PASSA | F11: =IF(F10=0,"-",IF(F10>=0.1,"PASSA",IF(F10>=0.05,"APERTADO","FALHA"))) -> PASSA | G11: =IF(G10=0,"-",IF(G10>=0.1,"PASSA",IF(G10>=0.05,"APERTADO","FALHA"))) -> APERTADO | H11: =IF(H10=0,"-",IF(H10>=0.1,"PASSA",IF(H10>=0.05,"APERTADO","FALHA"))) -> PASSA
A13: CONDIÇÃO 3: Capex atletas / Vendas atletas | B13: ≤ 1,0x | C13: ='Operacional Puro'!C49 -> 1.7322705 | D13: ='Operacional Puro'!D49 -> 0.89791198 | E13: ='Operacional Puro'!E49 -> 3.8628474 | F13: ='Operacional Puro'!F49 -> 3.8628474 | G13: ='Operacional Puro'!G49 -> 1.2252839 | H13: ='Operacional Puro'!H49 -> 1.2252839
A14: → Status | C14: =IF(C13=0,"-",IF(C13<=1,"PASSA",IF(C13<=1.5,"APERTADO","FALHA"))) -> FALHA | D14: =IF(D13=0,"-",IF(D13<=1,"PASSA",IF(D13<=1.5,"APERTADO","FALHA"))) -> PASSA | E14: =IF(E13=0,"-",IF(E13<=1,"PASSA",IF(E13<=1.5,"APERTADO","FALHA"))) -> FALHA | F14: =IF(F13=0,"-",IF(F13<=1,"PASSA",IF(F13<=1.5,"APERTADO","FALHA"))) -> FALHA | G14: =IF(G13=0,"-",IF(G13<=1,"PASSA",IF(G13<=1.5,"APERTADO","FALHA"))) -> APERTADO | H14: =IF(H13=0,"-",IF(H13<=1,"PASSA",IF(H13<=1.5,"APERTADO","FALHA"))) -> APERTADO
A16: CONDIÇÃO 4: Caixa final / Saída op. mensal | B16: ≥ 1,0 mês | C16: =(BP!C7+BP!C8)/((-DRE!C9-DRE!C14-DRE!C15)/12) -> 3.5056282 | D16: =(BP!D7+BP!D8)/((-DRE!D9-DRE!D14-DRE!D15)/12) -> 3.2814668 | E16: =(BP!E7+BP!E8)/((-DRE!E9-DRE!E14-DRE!E15)/12) -> 1.1882089 | F16: =(BP!F7+BP!F8)/((-DRE!F9-DRE!F14-DRE!F15)/12) -> 1.3995724 | G16: =(BP!G7+BP!G8)/((-DRE!G9-DRE!G14-DRE!G15)/12) -> 1.7588703 | H16: =(BP!H7+BP!H8)/((-DRE!H9-DRE!H14-DRE!H15)/12) -> 2.1177358
A17: → Status | C17: =IF(C16=0,"-",IF(C16>=2,"PASSA",IF(C16>=1,"APERTADO","FALHA"))) -> PASSA | D17: =IF(D16=0,"-",IF(D16>=2,"PASSA",IF(D16>=1,"APERTADO","FALHA"))) -> PASSA | E17: =IF(E16=0,"-",IF(E16>=2,"PASSA",IF(E16>=1,"APERTADO","FALHA"))) -> APERTADO | F17: =IF(F16=0,"-",IF(F16>=2,"PASSA",IF(F16>=1,"APERTADO","FALHA"))) -> APERTADO | G17: =IF(G16=0,"-",IF(G16>=2,"PASSA",IF(G16>=1,"APERTADO","FALHA"))) -> APERTADO | H17: =IF(H16=0,"-",IF(H16>=2,"PASSA",IF(H16>=1,"APERTADO","FALHA"))) -> PASSA
A19: RECEITA E CRESCIMENTO
A20: Receita Operacional Líquida (= DRE!6) | B20: R$ mil | C20: =DRE!C6 -> 979078 | D20: =DRE!D6 -> 1012380 | E20: =DRE!E6 -> 1142151 | F20: =DRE!F6 -> 1158862 | G20: =DRE!G6 -> 1393755 | H20: =DRE!H6 -> 1499741
A21: (-) Efeito FIFA 2025 (Mundial + Intercontinental) | B21: R$ mil | C21: ='Receita Detalhada'!C56 -> 10000 | D21: ='Receita Detalhada'!D56 -> 0 | E21: ='Receita Detalhada'!E56 -> 0 | F21: ='Receita Detalhada'!F56 -> 0 | G21: ='Receita Detalhada'!G56 -> 174200 | H21: ='Receita Detalhada'!H56 -> 174200
A22: Receita Recorrente Líquida | B22: R$ mil | C22: ='Operacional Puro'!C31 -> 969078 | D22: ='Operacional Puro'!D31 -> 1012380 | E22: ='Operacional Puro'!E31 -> 1142151 | F22: ='Operacional Puro'!F31 -> 1158862 | G22: ='Operacional Puro'!G31 -> 1219555 | H22: ='Operacional Puro'!H31 -> 1325541
A23: Crescimento YoY Receita Recorrente Líquida | B23: % | C23: - | D23: =IFERROR(D22/C22-1,0) -> 0.04468371 | E23: =IFERROR(E22/D22-1,0) -> 0.12818408 | F23: =IFERROR(F22/D22-1,0) -> 0.14469073 | G23: =IFERROR(G22/E22-1,0) -> 0.067770374 | H23: =IFERROR(H22/F22-1,0) -> 0.1438299
A25: RESULTADO E MARGENS
A26: Superávit/(Déficit) do exercício (= DRE!28) | B26: R$ mil | C26: =DRE!C28 -> 135690 | D26: =DRE!D28 -> 319545 | E26: =DRE!E28 -> -734 | F26: =DRE!F28 -> -2601 | G26: =DRE!G28 -> 335665 | H26: =DRE!H28 -> 343171
A27: EBITDA Reportado (= Op. Puro!11) | B27: R$ mil | C27: ='Operacional Puro'!C11 -> 286332 | D27: ='Operacional Puro'!D11 -> 475159 | E27: ='Operacional Puro'!E11 -> 269021 | F27: ='Operacional Puro'!F11 -> 271146 | G27: ='Operacional Puro'!G11 -> 569246 | H27: ='Operacional Puro'!H11 -> 607227
A28: EBITDA Recorrente Puro (= Op. Puro!26) | B28: R$ mil | C28: ='Operacional Puro'!C26 -> 151827 | D28: ='Operacional Puro'!D26 -> 234548 | E28: ='Operacional Puro'!E26 -> 217095 | F28: ='Operacional Puro'!F26 -> 215755 | G28: ='Operacional Puro'!G26 -> 83491 | H28: ='Operacional Puro'!H26 -> 135411
A29: Margem EBITDA Reportado | B29: % | C29: ='Operacional Puro'!C33 -> 0.29245065 | D29: ='Operacional Puro'!D33 -> 0.46934847 | E29: ='Operacional Puro'!E33 -> 0.23553891 | F29: ='Operacional Puro'!F33 -> 0.23397609 | G29: ='Operacional Puro'!G33 -> 0.40842616 | H29: ='Operacional Puro'!H33 -> 0.40488791
A30: Margem EBITDA Recorrente Puro | B30: % | C30: ='Operacional Puro'!C34 -> 0.1566716 | D30: ='Operacional Puro'!D34 -> 0.2316798 | E30: ='Operacional Puro'!E34 -> 0.19007557 | F30: ='Operacional Puro'!F34 -> 0.18617834 | G30: ='Operacional Puro'!G34 -> 0.068460217 | H30: ='Operacional Puro'!H34 -> 0.10215527
A32: ESTRUTURA FINANCEIRA — CAIXA E DÍVIDA OPERACIONAL
A33: Caixa LIVRE (BP!7) | B33: R$ mil | C33: =BP!C7 -> 236887 | D33: =BP!D7 -> 234487 | E33: =BP!E7 -> 70557 | F33: =BP!F7 -> 91841 | G33: =BP!G7 -> 143941 | H33: =BP!H7 -> 191714
A34: Caixa restrito (BP!8) | B34: R$ mil | C34: =BP!C8 -> 17581 | D34: =BP!D8 -> 28073 | E34: =BP!E8 -> 41662 | F34: =BP!F8 -> 41662 | G34: =BP!G8 -> 51140 | H34: =BP!H8 -> 51140
A35: Caixa TOTAL (livre + restrito) | B35: R$ mil | C35: =IFERROR(C33+C34,0) -> 254468 | D35: =IFERROR(D33+D34,0) -> 262560 | E35: =IFERROR(E33+E34,0) -> 112219 | F35: =IFERROR(F33+F34,0) -> 133503 | G35: =IFERROR(G33+G34,0) -> 195081 | H35: =IFERROR(H33+H34,0) -> 242854
A36: C/P jogadores total (CP + LP) | B36: R$ mil | C36: 214539 | D36: 234229 | E36: 369280 | F36: 369280 | G36: 561080 | H36: 497310
A37: C/R jogadores total (CP + LP) | B37: R$ mil | C37: 90855 | D37: 177619 | E37: 149033 | F37: 149033 | G37: 278998 | H37: 278998
A38: Parcelamentos PROFUT + PERSE | B38: R$ mil | C38: 210000 | D38: 167152 | E38: 165358 | F38: 165358 | G38: 162316 | H38: 162316
A39: Empréstimos bancários (BP!33 + BP!42) | B39: R$ mil | C39: =BP!C33+BP!C42 -> 35948 | D39: =BP!D33+BP!D42 -> 0 | E39: =BP!E33+BP!E42 -> 0 | F39: =BP!F33+BP!F42 -> 0 | G39: =BP!G33+BP!G42 -> 0 | H39: =BP!H33+BP!H42 -> 0
A41: DÍVIDA OPERACIONAL LÍQUIDA (DOL) | B41: R$ mil | C41: =C39+C38+C36-C37-C33 -> 132745 | D41: =D39+D38+D36-D37-D33 -> -10725 | E41: =E39+E38+E36-E37-E33 -> 315048 | F41: =F39+F38+F36-F37-F33 -> 293764 | G41: =G39+G38+G36-G37-G33 -> 300457 | H41: =H39+H38+H36-H37-H33 -> 188914
A42: Alavancagem (DOL / EBITDA Reportado) | B42: x | C42: =IFERROR(C41/C27,0) -> 0.46360519 | D42: =IFERROR(D41/D27,0) -> -0.022571392 | E42: =IFERROR(E41/E27,0) -> 1.1710907 | F42: =IFERROR(F41/F27,0) -> 1.0834163 | G42: =IFERROR(G41/G27,0) -> 0.52781574 | H42: =IFERROR(H41/H27,0) -> 0.31110935
A44: CAPITAL DE GIRO
A45: Ativo Circulante (BP!14) | B45: R$ mil | C45: =BP!C14 -> 343558 | D45: =BP!D14 -> 455914 | E45: =BP!E14 -> 321870 | F45: =BP!F14 -> 347343 | G45: =BP!G14 -> 558966 | H45: =BP!H14 -> 604975
A46: Passivo Circulante (BP!38) | B46: R$ mil | C46: =BP!C38 -> 392167 | D46: =BP!D38 -> 375282 | E46: =BP!E38 -> 504785 | F46: =BP!F38 -> 529801 | G46: =BP!G38 -> 592332 | H46: =BP!H38 -> 646588
A47: Capital Circulante Líquido (CCL) | B47: R$ mil | C47: =IFERROR(C45-C46,0) -> -48609 | D47: =IFERROR(D45-D46,0) -> 80632 | E47: =IFERROR(E45-E46,0) -> -182915 | F47: =IFERROR(F45-F46,0) -> -182458 | G47: =IFERROR(G45-G46,0) -> -33366 | H47: =IFERROR(H45-H46,0) -> -41613
A48: Liquidez Corrente (AC / PC) | B48: x | C48: =IFERROR(C45/C46,0) -> 0.87605025 | D48: =IFERROR(D45/D46,0) -> 1.2148571 | E48: =IFERROR(E45/E46,0) -> 0.63763781 | F48: =IFERROR(F45/F46,0) -> 0.65561031 | G48: =IFERROR(G45/G46,0) -> 0.9436701 | H48: =IFERROR(H45/H46,0) -> 0.93564217
A50: CAPEX E VENDAS DE ATLETAS
A51: Capex contábil de atletas (= Op. Puro!46) | B51: R$ mil | C51: ='Operacional Puro'!C46 -> 231000 | D51: ='Operacional Puro'!D46 -> 272510 | E51: ='Operacional Puro'!E46 -> 414808 | F51: ='Operacional Puro'!F46 -> 414808 | G51: ='Operacional Puro'!G46 -> 635605 | H51: ='Operacional Puro'!H46 -> 635605
A52: Receita de venda de atletas (= Op. Puro!47) | B52: R$ mil | C52: ='Operacional Puro'!C47 -> 133351 | D52: ='Operacional Puro'!D47 -> 303493 | E52: ='Operacional Puro'!E47 -> 107384 | F52: ='Operacional Puro'!F47 -> 107384 | G52: ='Operacional Puro'!G47 -> 518741 | H52: ='Operacional Puro'!H47 -> 518741
A53: Capex líquido (Capex − Vendas) | B53: R$ mil | C53: =IFERROR(C51-C52,0) -> 97649 | D53: =IFERROR(D51-D52,0) -> -30983 | E53: =IFERROR(E51-E52,0) -> 307424 | F53: =IFERROR(F51-F52,0) -> 307424 | G53: =IFERROR(G51-G52,0) -> 116864 | H53: =IFERROR(H51-H52,0) -> 116864
A54: Capex / Vendas (Condição 3) | B54: x | C54: ='Operacional Puro'!C49 -> 1.7322705 | D54: ='Operacional Puro'!D49 -> 0.89791198 | E54: ='Operacional Puro'!E49 -> 3.8628474 | F54: ='Operacional Puro'!F49 -> 3.8628474 | G54: ='Operacional Puro'!G49 -> 1.2252839 | H54: ='Operacional Puro'!H49 -> 1.2252839
A56: FOLHA AMPLIADA
A57: Folha ampliada total (= Op. Puro!40) | B57: R$ mil | C57: ='Operacional Puro'!C40 -> 438436 | D57: ='Operacional Puro'!D40 -> 463050 | E57: ='Operacional Puro'!E40 -> 524040 | F57: ='Operacional Puro'!F40 -> 524040 | G57: ='Operacional Puro'!G40 -> 696183 | H57: ='Operacional Puro'!H40 -> 711094
A58: Folha / Receita Op Líquida (= Op. Puro!42) | B58: % | C58: ='Operacional Puro'!C42 -> 0.44780498 | D58: ='Operacional Puro'!D42 -> 0.45738754 | E58: ='Operacional Puro'!E42 -> 0.45881849 | F58: ='Operacional Puro'!F42 -> 0.45220225 | G58: ='Operacional Puro'!G42 -> 0.49950171 | H58: ='Operacional Puro'!H42 -> 0.47414454
A59: Folha / Receita Recorrente (Condição 1) | B59: % | C59: ='Operacional Puro'!C43 -> 0.45242591 | D59: ='Operacional Puro'!D43 -> 0.45738754 | E59: ='Operacional Puro'!E43 -> 0.45881849 | F59: ='Operacional Puro'!F43 -> 0.45220225 | G59: ='Operacional Puro'!G43 -> 0.57085002 | H59: ='Operacional Puro'!H43 -> 0.53645568
A61: PATRIMÔNIO LÍQUIDO
A62: Patrimônio líquido total (= BP!56) | B62: R$ mil | C62: =BP!C56 -> 334546 | D62: =BP!D56 -> 654091 | E62: =BP!E56 -> 618460 | F62: =BP!F56 -> 619753 | G62: =BP!G56 -> 954125 | H62: =BP!H56 -> 957566
A63: Crescimento YoY PL | B63: % | C63: - | D63: =IFERROR(D62/C62-1,0) -> 0.95516013 | E63: =IFERROR(E62/D62-1,0) -> -0.054474072 | F63: =IFERROR(F62/D62-1,0) -> -0.052497282 | G63: =IFERROR(G62/E62-1,0) -> 0.54274327 | H63: =IFERROR(H62/F62-1,0) -> 0.54507683
A65: GERAÇÃO DE CAIXA
A66: Caixa Operacional (= DFC!27) | B66: R$ mil | C66: =DFC!C27 -> 257346 | D66: =DFC!D27 -> 351089 | E66: =DFC!E27 -> 408515 | F66: =DFC!F27 -> 421231 | G66: =DFC!G27 -> 599263 | H66: =DFC!H27 -> 679990
A67: Caixa Investimento (= DFC!36) | B67: R$ mil | C67: =DFC!C36 -> 0 | D67: =DFC!D36 -> -312929 | E67: =DFC!E36 -> -564647 | F67: =DFC!F36 -> -559238 | G67: =DFC!G36 -> -517121 | H67: =DFC!H36 -> -557978
A68: Free Cash Flow (Op + Inv) | B68: R$ mil | C68: =DFC!C38 -> 257346 | D68: =DFC!D38 -> 38160 | E68: =DFC!E38 -> -156132 | F68: =DFC!F38 -> -138007 | G68: =DFC!G38 -> 82142 | H68: =DFC!H38 -> 122012
A69: Capex CAIXA atletas (= DFC!30 invertido) | B69: R$ mil | C69: =-DFC!C30 -> 0 | D69: =-DFC!D30 -> 0 | E69: =-DFC!E30 -> 382368 | F69: =-DFC!F30 -> 382368 | G69: =-DFC!G30 -> 507575 | H69: =-DFC!H30 -> 507575
A71: Notas críticas:
A72: • Síntese das 4 Condições no topo: PASSA (verde) = margem confortável; APERTADO (amarelo) = no limite; FALHA (vermelho) = condição não atendida.
A73: • Critério COND 1: folha ≤ 50% PASSA; 50-65% APERTADO; >65% FALHA.
A74: • Critério COND 2: margem EBITDA Rec. Puro ≥ 10% PASSA; 5-10% APERTADO; <5% FALHA.
A75: • Critério COND 3: Capex/Vendas ≤ 1,0x PASSA; 1,0-1,5x APERTADO; >1,5x FALHA.
A76: • Critério COND 4: Caixa total / Saída op. mensal ≥ 2 meses PASSA; 1-2 meses APERTADO; <1 mês FALHA.
A77: • DOL (linha 41) calculada como: Empréstimos + Parcelamentos PROFUT/PERSE + C/P jogadores − C/R jogadores − Caixa livre.
A78: • DOL CALCULADA pode divergir do REPORTADO pelo clube (R$ 174 mi IPCA 2025 Consol vs ~189 mi calculado nominal). Diferença vem da metodologia (clube possivelmente usa outra base ou ajustes IPCA).
A79: • C/P jogadores Cont 2024 e 2025: BP Cont agrega Fornecedores + C/P jogadores numa linha (R$ 561.080 em 2025). Para Consol, usamos a NE 9 que destaca jogadores apenas (R$ 497.310). Para Cont, valor pode estar levemente sobrestimado.
A80: • Parcelamentos 2022 (R$ 210.000) é estimativa — handoff não tem NE 10 detalhada para 2022.
A81: • Crescimento YoY do PL 2025 Cont: +54% (de 618 para 954 mi) — o maior salto histórico.
A82: • Alavancagem (linha 42) caiu de 1,21x (2024) para 0,30x (2025) — efeito da explosão do EBITDA Reportado por premiações FIFA.
A83: • EBITDA Recorrente Puro 2025 (R$ 83 mi) NÃO sustenta o nível de DOL atual sem novas vendas grandes. Esse é o vetor de fragilidade central para 2026-2027.

Sheet Premissas Runway
A1: Premissas Runway — Cenários 2026-2027
A2: Células em AMARELO são editáveis | R$ milhares nominais | Base: realizado 2025 Consolidado
A4: Premissa | B4: Realizado 2025 | C4: CENÁRIO OTIMISTA | E4: CENÁRIO BASE | G4: CENÁRIO PESSIMISTA
C5: 2026 | D5: 2027 | E5: 2026 | F5: 2027 | G5: 2026 | H5: 2027
A7: CENÁRIOS ESPORTIVOS — descrição qualitativa
A8: Brasileirão | B8: Campeão | C8: Top 2 | D8: Top 2 | E8: Top 4 | F8: Top 4 | G8: Top 6 | H8: Top 6
A9: Libertadores | B9: Campeão | C9: Semifinal | D9: Final | E9: Quartas | F9: Quartas | G9: Oitavas | H9: Fora
A10: Copa do Brasil | B10: Oitavas | C10: Semifinal | D10: Campeão | E10: Quartas | F10: Quartas | G10: Oitavas | H10: Oitavas
A11: Carioca | B11: Campeão | C11: Campeão | D11: Campeão | E11: Final | F11: Campeão | G11: Semifinal | H11: Final
A12: Eventos FIFA (Mundial 2029 / Intercontinental anual) | B12: Mundial+Intercont. | C12: Intercont. | D12: Intercont. | E12: - | F12: Intercont. | G12: - | H12: -
A14: RECEITA — Crescimento por categoria (% YoY sobre o ano anterior)
A15: Broadcast (transmissão + premiações sem FIFA + mídia) | B15: 437800 | C15: 0.08 | D15: 0.07 | E15: 0.03 | F15: 0.03 | G15: -0.02 | H15: -0.01
A16: Comercial (patrocínio + licenciamento) | B16: 541000 | C16: 0.1 | D16: 0.08 | E16: 0.05 | F16: 0.04 | G16: -0.01 | H16: 0
A17: Matchday (bilheteria + sócio + estádio + camarotes) | B17: 322000 | C17: 0.05 | D17: 0.05 | E17: 0.02 | F17: 0.02 | G17: -0.02 | H17: -0.01
A18: Diversos (clube social + amadores + tour Maracanã) | B18: 96000 | C18: 0.05 | D18: 0.04 | E18: 0.03 | F18: 0.02 | G18: 0 | H18: 0
A20: PREMIAÇÕES NÃO-RECORRENTES FIFA — R$ mil nominais
A21: Prêmio FIFA Mundial (anual, R$ mil) | B21: 174200 | C21: 0 | D21: 0 | E21: 0 | F21: 0 | G21: 0 | H21: 0
A22: Prêmio FIFA Intercontinental (anual, R$ mil) | B22: 21600 | C22: 21600 | D22: 21600 | E22: 0 | F22: 21600 | G22: 0 | H22: 0
A24: FOLHA AMPLIADA — Crescimento YoY
A25: Folha ampliada (% YoY sobre o ano anterior) — base R$ 711 mi 2025 Consol | B25: 711094 | C25: 0.12 | D25: 0.08 | E25: 0.07 | F25: 0.05 | G25: 0.04 | H25: 0.02
A27: CAPEX E VENDAS DE ATLETAS — R$ mil nominais
A28: Capex contábil de atletas (R$ mil) | B28: 635605 | C28: 600000 | D28: 550000 | E28: 450000 | F28: 400000 | G28: 320000 | H28: 250000
A29: Receita de venda de atletas (R$ mil) | B29: 518741 | C29: 450000 | D29: 500000 | E29: 300000 | F29: 350000 | G29: 200000 | H29: 200000
A31: OUTROS CUSTOS E DESPESAS — Crescimento YoY
A32: Gastos com jogos e competições | B32: 131954 | C32: 0.05 | D32: 0.04 | E32: 0.03 | F32: 0.02 | G32: -0.05 | H32: -0.03
A33: Despesas administrativas | B33: 142285 | C33: 0.08 | D33: 0.05 | E33: 0.05 | F33: 0.03 | G33: 0.03 | H33: 0.02
A34: Despesas comerciais | B34: 39610 | C34: 0.05 | D34: 0.05 | E34: 0.03 | F34: 0.03 | G34: 0 | H34: 0
A35: Outros custos pulverizados (materiais, manutenção, serviços) | B35: 99844 | C35: 0.05 | D35: 0.04 | E35: 0.03 | F35: 0.02 | G35: 0 | H35: 0
A37: AMORTIZAÇÕES
A38: Amortização atletas — % do Capex contábil do ano | B38: 0.38 | C38: 0.4 | D38: 0.45 | E38: 0.4 | F38: 0.42 | G38: 0.42 | H38: 0.45
A39: Depreciação imobilizado e outras amortizações | B39: 12625 | C39: 15000 | D39: 18000 | E39: 14000 | F39: 15000 | G39: 13000 | H39: 13500
A41: OUTROS ITENS RELEVANTES
A42: Resultado financeiro líquido (R$ mil) | B42: 6991 | C42: 10000 | D42: 5000 | E42: 0 | F42: -5000 | G42: -15000 | H42: -20000
A43: Equivalência patrimonial Fla-Flu (Cont — informativo) | B43: 13939 | C43: 15000 | D43: 18000 | E43: 10000 | F43: 12000 | G43: 5000 | H43: 5000
A44: Reversão líquida de contingências (assume zero recorrente) | B44: 23246 | C44: 0 | D44: 0 | E44: 0 | F44: 0 | G44: 0 | H44: 0
A45: Ganho Hilton Rio By Yoo (estimativa, R$ mil) | B45: 7010 | C45: 5000 | D45: 3000 | E45: 4000 | F45: 2000 | G45: 3000 | H45: 1500
A46: Pagamento de parcelamentos PROFUT/PERSE | B46: 8758 | C46: 15832 | D46: 15832 | E46: 15832 | F46: 15832 | G46: 15832 | H46: 15832
A47: Pagamento de outorga Maracanã (Consolidado) | B47: 20061 | C47: 22000 | D47: 23000 | E47: 22000 | F47: 23000 | G47: 22000 | H47: 23000
A49: Notas críticas:
A50: • Premissas em AMARELO são editáveis — todos os cenários podem ser ajustados.
A51: • REALIZADO 2025 (coluna B) é referência fixa — não editar.
A52: • Otimista: ciclo continua girando — títulos sustentam premiações, base entrega novos vendáveis, Capex agressivo se autofinancia via vendas.
A53: • Base: estabilização — ciclo desacelera mas não inverte. Premiações caem (sem Mundial), folha pressiona, vendas moderadas.
A54: • Pessimista: ciclo inverte — sem títulos, sem premiações altas, Capex contrai, base estagna, folha já contratada continua subindo. Demonstra a fragilidade central do eixo.
A55: • Capex 2026 (todos os cenários) já incorpora o que SE SABE: Paquetá R$ 270 mi + Vitor Eduardo + Andrew = ~R$ 320 mi confirmado em janeiro/2026. Pessimista assume zero novo Capex pelo resto do ano.
A56: • Folha já está parcialmente contratada para 2026 — mesmo no Pessimista, o crescimento mínimo é +4% (custo de contratos vigentes + 13º salário + reajustes de equipe administrativa).
A57: • Eventos FIFA (linhas 21-22): Mundial só em 2029. Intercontinental anual depende de ganhar Libertadores anterior — Otimista assume continuidade, Base assume só 2027, Pessimista assume zero.
A58: • Amortização de atletas: proxy de 40-45% do Capex do ano (compatível com vida útil média de 2-3 anos dos contratos).
A59: • Cronograma PROFUT/PERSE 2026 e 2027: R$ 15.832/ano cada (handoff NE 10), independente do cenário.
A60: • Estes valores alimentam a aba Modelo Runway — alterações aqui propagam automaticamente.

Sheet Modelo Runway
A1: Modelo Runway — Projeções 2026 e 2027 nos 3 Cenários
A2: DFC simplificada | R$ milhares nominais | Base Consolidado | Toda linha azul puxa de Premissas Runway
A4: Linha | B4: Realizado 2025 | C4: CENÁRIO OTIMISTA | E4: CENÁRIO BASE | G4: CENÁRIO PESSIMISTA
C5: 2026 | D5: 2027 | E5: 2026 | F5: 2027 | G5: 2026 | H5: 2027
A7: RECEITA RECORRENTE (sem efeitos FIFA Mundial/Intercontinental)
A8: Broadcast (transmissão + premiações sem FIFA + mídia) | B8: 437800 | C8: =B8*(1+'Premissas Runway'!C15) -> 472824 | D8: =C8*(1+'Premissas Runway'!D15) -> 505921.68 | E8: =B8*(1+'Premissas Runway'!E15) -> 450934 | F8: =E8*(1+'Premissas Runway'!F15) -> 464462.02 | G8: =B8*(1+'Premissas Runway'!G15) -> 429044 | H8: =G8*(1+'Premissas Runway'!H15) -> 424753.56
A9: Comercial (patrocínio + licenciamento) | B9: 541000 | C9: =B9*(1+'Premissas Runway'!C16) -> 595100 | D9: =C9*(1+'Premissas Runway'!D16) -> 642708 | E9: =B9*(1+'Premissas Runway'!E16) -> 568050 | F9: =E9*(1+'Premissas Runway'!F16) -> 590772 | G9: =B9*(1+'Premissas Runway'!G16) -> 535590 | H9: =G9*(1+'Premissas Runway'!H16) -> 535590
A10: Matchday (bilheteria + sócio + estádio + camarotes) | B10: 322000 | C10: =B10*(1+'Premissas Runway'!C17) -> 338100 | D10: =C10*(1+'Premissas Runway'!D17) -> 355005 | E10: =B10*(1+'Premissas Runway'!E17) -> 328440 | F10: =E10*(1+'Premissas Runway'!F17) -> 335008.8 | G10: =B10*(1+'Premissas Runway'!G17) -> 315560 | H10: =G10*(1+'Premissas Runway'!H17) -> 312404.4
A11: Diversos (clube social + amadores + tour Maracanã) | B11: 96000 | C11: =B11*(1+'Premissas Runway'!C18) -> 100800 | D11: =C11*(1+'Premissas Runway'!D18) -> 104832 | E11: =B11*(1+'Premissas Runway'!E18) -> 98880 | F11: =E11*(1+'Premissas Runway'!F18) -> 100857.6 | G11: =B11*(1+'Premissas Runway'!G18) -> 96000 | H11: =G11*(1+'Premissas Runway'!H18) -> 96000
A13: (=) RECEITA RECORRENTE BRUTA | B13: =B8+B9+B10+B11 -> 1396800 | C13: =C8+C9+C10+C11 -> 1506824 | D13: =D8+D9+D10+D11 -> 1608466.7 | E13: =E8+E9+E10+E11 -> 1446304 | F13: =F8+F9+F10+F11 -> 1491100.4 | G13: =G8+G9+G10+G11 -> 1376194 | H13: =H8+H9+H10+H11 -> 1368748
A14: (-) Deduções (PIS folha + INSS receita ~5%) | B14: =-B13*0.05 -> -69840 | C14: =-C13*0.05 -> -75341.2 | D14: =-D13*0.05 -> -80423.334 | E14: =-E13*0.05 -> -72315.2 | F14: =-F13*0.05 -> -74555.021 | G14: =-G13*0.05 -> -68809.7 | H14: =-H13*0.05 -> -68437.398
A15: RECEITA RECORRENTE LÍQUIDA (sem FIFA) | B15: =B13+B14 -> 1326960 | C15: =C13+C14 -> 1431482.8 | D15: =D13+D14 -> 1528043.3 | E15: =E13+E14 -> 1373988.8 | F15: =F13+F14 -> 1416545.4 | G15: =G13+G14 -> 1307384.3 | H15: =H13+H14 -> 1300310.6
A17: EFEITO FIFA NÃO-RECORRENTE
A18: (+) Prêmio FIFA Mundial (= Premissas!21) | B18: ='Premissas Runway'!B21 -> 174200 | C18: ='Premissas Runway'!C21 -> 0 | D18: ='Premissas Runway'!D21 -> 0 | E18: ='Premissas Runway'!E21 -> 0 | F18: ='Premissas Runway'!F21 -> 0 | G18: ='Premissas Runway'!G21 -> 0 | H18: ='Premissas Runway'!H21 -> 0
A19: (+) Prêmio FIFA Intercontinental (= Premissas!22) | B19: ='Premissas Runway'!B22 -> 21600 | C19: ='Premissas Runway'!C22 -> 21600 | D19: ='Premissas Runway'!D22 -> 21600 | E19: ='Premissas Runway'!E22 -> 0 | F19: ='Premissas Runway'!F22 -> 21600 | G19: ='Premissas Runway'!G22 -> 0 | H19: ='Premissas Runway'!H22 -> 0
A21: (=) RECEITA OPERACIONAL LÍQUIDA TOTAL | B21: =B15+B18+B19 -> 1522760 | C21: =C15+C18+C19 -> 1453082.8 | D21: =D15+D18+D19 -> 1549643.3 | E21: =E15+E18+E19 -> 1373988.8 | F21: =F15+F18+F19 -> 1438145.4 | G21: =G15+G18+G19 -> 1307384.3 | H21: =H15+H18+H19 -> 1300310.6
A23: CUSTOS OPERACIONAIS
A24: (-) Folha ampliada (salários + DI) | B24: -711094 | C24: =B24*(1+'Premissas Runway'!C25) -> -796425.28 | D24: =C24*(1+'Premissas Runway'!D25) -> -860139.3 | E24: =B24*(1+'Premissas Runway'!E25) -> -760870.58 | F24: =E24*(1+'Premissas Runway'!F25) -> -798914.11 | G24: =B24*(1+'Premissas Runway'!G25) -> -739537.76 | H24: =G24*(1+'Premissas Runway'!H25) -> -754328.52
A25: (-) Gastos com jogos e competições | B25: -131954 | C25: =B25*(1+'Premissas Runway'!C32) -> -138551.7 | D25: =C25*(1+'Premissas Runway'!D32) -> -144093.77 | E25: =B25*(1+'Premissas Runway'!E32) -> -135912.62 | F25: =E25*(1+'Premissas Runway'!F32) -> -138630.87 | G25: =B25*(1+'Premissas Runway'!G32) -> -125356.3 | H25: =G25*(1+'Premissas Runway'!H32) -> -121595.61
A26: (-) Despesas administrativas | B26: -142285 | C26: =B26*(1+'Premissas Runway'!C33) -> -153667.8 | D26: =C26*(1+'Premissas Runway'!D33) -> -161351.19 | E26: =B26*(1+'Premissas Runway'!E33) -> -149399.25 | F26: =E26*(1+'Premissas Runway'!F33) -> -153881.23 | G26: =B26*(1+'Premissas Runway'!G33) -> -146553.55 | H26: =G26*(1+'Premissas Runway'!H33) -> -149484.62
A27: (-) Despesas comerciais | B27: -39610 | C27: =B27*(1+'Premissas Runway'!C34) -> -41590.5 | D27: =C27*(1+'Premissas Runway'!D34) -> -43670.025 | E27: =B27*(1+'Premissas Runway'!E34) -> -40798.3 | F27: =E27*(1+'Premissas Runway'!F34) -> -42022.249 | G27: =B27*(1+'Premissas Runway'!G34) -> -39610 | H27: =G27*(1+'Premissas Runway'!H34) -> -39610
A28: (-) Outros custos pulverizados | B28: -99844 | C28: =B28*(1+'Premissas Runway'!C35) -> -104836.2 | D28: =C28*(1+'Premissas Runway'!D35) -> -109029.65 | E28: =B28*(1+'Premissas Runway'!E35) -> -102839.32 | F28: =E28*(1+'Premissas Runway'!F35) -> -104896.11 | G28: =B28*(1+'Premissas Runway'!G35) -> -99844 | H28: =G28*(1+'Premissas Runway'!H35) -> -99844
A30: Total custos operacionais (ex-amortização) | B30: =SUM(B24:B28) -> -1124787 | C30: =SUM(C24:C28) -> -1235071.5 | D30: =SUM(D24:D28) -> -1318283.9 | E30: =SUM(E24:E28) -> -1189820.1 | F30: =SUM(F24:F28) -> -1238344.6 | G30: =SUM(G24:G28) -> -1150901.6 | H30: =SUM(H24:H28) -> -1164862.7
A32: EBITDA PROJETADO
A33: EBITDA OPERACIONAL (Receita Total - Custos) | B33: =B21+B30 -> 397973 | C33: =C21+C30 -> 218011.32 | D33: =D21+D30 -> 231359.41 | E33: =E21+E30 -> 184168.73 | F33: =F21+F30 -> 199800.83 | G33: =G21+G30 -> 156482.69 | H33: =H21+H30 -> 135447.81
A34: EBITDA RECORRENTE PURO (sem FIFA) | B34: =B15+B30 -> 202173 | C34: =C15+C30 -> 196411.32 | D34: =D15+D30 -> 209759.41 | E34: =E15+E30 -> 184168.73 | F34: =F15+F30 -> 178200.83 | G34: =G15+G30 -> 156482.69 | H34: =H15+H30 -> 135447.81
A35: Margem EBITDA Recorrente Puro / Rec. Recorrente Líquida | B35: =IFERROR(B34/B15,0) -> 0.15235802 | C35: =IFERROR(C34/C15,0) -> 0.1372083 | D35: =IFERROR(D34/D15,0) -> 0.13727321 | E35: =IFERROR(E34/E15,0) -> 0.13403947 | F35: =IFERROR(F34/F15,0) -> 0.12579959 | G35: =IFERROR(G34/G15,0) -> 0.11969143 | H35: =IFERROR(H34/H15,0) -> 0.10416574
A37: VENDA DE ATLETAS E AJUSTES NÃO-OPERACIONAIS
A38: (+) Receita líquida venda de atletas (= Premissas!29) | B38: ='Premissas Runway'!B29 -> 518741 | C38: ='Premissas Runway'!C29 -> 450000 | D38: ='Premissas Runway'!D29 -> 500000 | E38: ='Premissas Runway'!E29 -> 300000 | F38: ='Premissas Runway'!F29 -> 350000 | G38: ='Premissas Runway'!G29 -> 200000 | H38: ='Premissas Runway'!H29 -> 200000
A39: (Ganho líquido estimado — margem média 51% sobre vendas) | B39: =B38*0.51 -> 264557.91 | C39: =C38*0.51 -> 229500 | D39: =D38*0.51 -> 255000 | E39: =E38*0.51 -> 153000 | F39: =F38*0.51 -> 178500 | G39: =G38*0.51 -> 102000 | H39: =H38*0.51 -> 102000
A40: (+) Equivalência Fla-Flu + Ganho Hilton (= Premissas!43+45) | B40: ='Premissas Runway'!B43+'Premissas Runway'!B45 -> 20949 | C40: ='Premissas Runway'!C43+'Premissas Runway'!C45 -> 20000 | D40: ='Premissas Runway'!D43+'Premissas Runway'!D45 -> 21000 | E40: ='Premissas Runway'!E43+'Premissas Runway'!E45 -> 14000 | F40: ='Premissas Runway'!F43+'Premissas Runway'!F45 -> 14000 | G40: ='Premissas Runway'!G43+'Premissas Runway'!G45 -> 8000 | H40: ='Premissas Runway'!H43+'Premissas Runway'!H45 -> 6500
A41: (+) Resultado financeiro líquido (= Premissas!42) | B41: ='Premissas Runway'!B42 -> 6991 | C41: ='Premissas Runway'!C42 -> 10000 | D41: ='Premissas Runway'!D42 -> 5000 | E41: ='Premissas Runway'!E42 -> 0 | F41: ='Premissas Runway'!F42 -> -5000 | G41: ='Premissas Runway'!G42 -> -15000 | H41: ='Premissas Runway'!H42 -> -20000
A43: CAPEX DE ATLETAS
A44: (-) Capex contábil atletas (= Premissas!28) | B44: =-'Premissas Runway'!B28 -> -635605 | C44: =-'Premissas Runway'!C28 -> -600000 | D44: =-'Premissas Runway'!D28 -> -550000 | E44: =-'Premissas Runway'!E28 -> -450000 | F44: =-'Premissas Runway'!F28 -> -400000 | G44: =-'Premissas Runway'!G28 -> -320000 | H44: =-'Premissas Runway'!H28 -> -250000
A45: (Pagamento CAIXA estimado: Capex × 80%) | B45: =B44*0.8 -> -508484 | C45: =C44*0.8 -> -480000 | D45: =D44*0.8 -> -440000 | E45: =E44*0.8 -> -360000 | F45: =F44*0.8 -> -320000 | G45: =G44*0.8 -> -256000 | H45: =H44*0.8 -> -200000
A47: CAIXA OPERACIONAL SIMPLIFICADO (proxy do Free Cash Flow)
A48: Caixa Operacional Proxy = EBITDA + Ganho Vendas + Outros + Financ. | B48: =B33+B39+B40+B41 -> 690470.91 | C48: =C33+C39+C40+C41 -> 477511.32 | D48: =D33+D39+D40+D41 -> 512359.41 | E48: =E33+E39+E40+E41 -> 351168.73 | F48: =F33+F39+F40+F41 -> 387300.83 | G48: =G33+G39+G40+G41 -> 251482.69 | H48: =H33+H39+H40+H41 -> 223947.81
A49: (-) Capex CAIXA (= 80% do Capex contábil) | B49: =B45 -> -508484 | C49: =C45 -> -480000 | D49: =D45 -> -440000 | E49: =E45 -> -360000 | F49: =F45 -> -320000 | G49: =G45 -> -256000 | H49: =H45 -> -200000
A50: (-) Pagamento parcelamentos PROFUT/PERSE | B50: =-'Premissas Runway'!B46 -> -8758 | C50: =-'Premissas Runway'!C46 -> -15832 | D50: =-'Premissas Runway'!D46 -> -15832 | E50: =-'Premissas Runway'!E46 -> -15832 | F50: =-'Premissas Runway'!F46 -> -15832 | G50: =-'Premissas Runway'!G46 -> -15832 | H50: =-'Premissas Runway'!H46 -> -15832
A51: (-) Pagamento outorga Maracanã (Consol) | B51: =-'Premissas Runway'!B47 -> -20061 | C51: =-'Premissas Runway'!C47 -> -22000 | D51: =-'Premissas Runway'!D47 -> -23000 | E51: =-'Premissas Runway'!E47 -> -22000 | F51: =-'Premissas Runway'!F47 -> -23000 | G51: =-'Premissas Runway'!G47 -> -22000 | H51: =-'Premissas Runway'!H47 -> -23000
A53: VARIAÇÃO DE CAIXA E SALDO FINAL
A54: VARIAÇÃO LÍQUIDA DO CAIXA | B54: =B48+B49+B50+B51 -> 153167.91 | C54: =C48+C49+C50+C51 -> -40320.68 | D54: =D48+D49+D50+D51 -> 33527.413 | E54: =E48+E49+E50+E51 -> -46663.27 | F54: =F48+F49+F50+F51 -> 28468.835 | G54: =G48+G49+G50+G51 -> -42349.31 | H54: =H48+H49+H50+H51 -> -14884.185
A55: Caixa total inicial (livre + restrito) | B55: =BP!H7+BP!H8 -> 242854 | C55: =BP!H7+BP!H8 -> 242854 | D55: =C56 -> 202533.32 | E55: =BP!H7+BP!H8 -> 242854 | F55: =E56 -> 196190.73 | G55: =BP!H7+BP!H8 -> 242854 | H55: =G56 -> 200504.69
A56: CAIXA TOTAL FINAL (livre + restrito) | B56: =B55+0 -> 242854 | C56: =C55+C54 -> 202533.32 | D56: =D55+D54 -> 236060.73 | E56: =E55+E54 -> 196190.73 | F56: =F55+F54 -> 224659.56 | G56: =G55+G54 -> 200504.69 | H56: =H55+H54 -> 185620.5
A58: Notas críticas:
A59: • Modelo DFC simplificado: NÃO é uma DFC completa nos moldes contábeis — é um proxy para análise de runway e sustentabilidade do caixa.
A60: • Toda linha em VERDE puxa direto de Premissas Runway. Alterações lá propagam aqui imediatamente.
A61: • Linha 30: 'Total custos operacionais' não inclui amortização de atletas (que não é caixa).
A62: • Linha 39: 'Ganho líquido venda atletas' usa margem média de 51% sobre a receita bruta de venda (média 2022-2025: ganho/receita varia de 44% a 73%).
A63: • Linha 45: 'Pagamento CAIXA' assume 80% do Capex contábil — proporção observada em 2024 (92%) e 2025 (80%).
A64: • Linha 48: 'Caixa Operacional Proxy' é uma aproximação grosseira — ignora variações de capital de giro (C/R jogadores, C/P jogadores não pagos no ano, adiantamentos).
A65: • Resultado financeiro líquido é input direto das Premissas — em cenário pessimista, vira negativo por aumento de correção monetária dos parcelamentos.
A66: • Para fechar Δ caixa real, há outros componentes (financiamento via C/P jogadores como entrada, variação capital de giro, etc.) — não modelados aqui por simplicidade.
A67: • Para análise narrativa do post, o que importa é: EBITDA Recorrente Puro (linha 34), Margem EBITDA (linha 35), e Caixa final (linha 56) em cada cenário.
A68: • Cenário Pessimista mostra a fragilidade do modelo: sem ciclo virtuoso de premiações + Capex, o EBITDA Puro e o caixa final encolhem rapidamente.

Sheet Resumo Cenários
A1: Resumo Cenários — Visão Consolidada 2025-2027
A2: Indicadores-chave em cada cenário | Toda linha em verde puxa de Modelo Runway
A4: Indicador | B4: Real. 2025 | C4: OTIMISTA | E4: BASE | G4: PESSIMISTA
C5: 2026 | D5: 2027 | E5: 2026 | F5: 2027 | G5: 2026 | H5: 2027
A7: RECEITA
A8: Receita Recorrente Líquida (sem FIFA) | B8: ='Modelo Runway'!B15 -> 1326960 | C8: ='Modelo Runway'!C15 -> 1431482.8 | D8: ='Modelo Runway'!D15 -> 1528043.3 | E8: ='Modelo Runway'!E15 -> 1373988.8 | F8: ='Modelo Runway'!F15 -> 1416545.4 | G8: ='Modelo Runway'!G15 -> 1307384.3 | H8: ='Modelo Runway'!H15 -> 1300310.6
A9: (+) Prêmio FIFA Mundial | B9: ='Modelo Runway'!B18 -> 174200 | C9: ='Modelo Runway'!C18 -> 0 | D9: ='Modelo Runway'!D18 -> 0 | E9: ='Modelo Runway'!E18 -> 0 | F9: ='Modelo Runway'!F18 -> 0 | G9: ='Modelo Runway'!G18 -> 0 | H9: ='Modelo Runway'!H18 -> 0
A10: (+) Prêmio FIFA Intercontinental | B10: ='Modelo Runway'!B19 -> 21600 | C10: ='Modelo Runway'!C19 -> 21600 | D10: ='Modelo Runway'!D19 -> 21600 | E10: ='Modelo Runway'!E19 -> 0 | F10: ='Modelo Runway'!F19 -> 21600 | G10: ='Modelo Runway'!G19 -> 0 | H10: ='Modelo Runway'!H19 -> 0
A11: Receita Operacional Líquida TOTAL | B11: ='Modelo Runway'!B21 -> 1522760 | C11: ='Modelo Runway'!C21 -> 1453082.8 | D11: ='Modelo Runway'!D21 -> 1549643.3 | E11: ='Modelo Runway'!E21 -> 1373988.8 | F11: ='Modelo Runway'!F21 -> 1438145.4 | G11: ='Modelo Runway'!G21 -> 1307384.3 | H11: ='Modelo Runway'!H21 -> 1300310.6
A13: EBITDA E RENTABILIDADE
A14: EBITDA Operacional Total | B14: ='Modelo Runway'!B33 -> 397973 | C14: ='Modelo Runway'!C33 -> 218011.32 | D14: ='Modelo Runway'!D33 -> 231359.41 | E14: ='Modelo Runway'!E33 -> 184168.73 | F14: ='Modelo Runway'!F33 -> 199800.83 | G14: ='Modelo Runway'!G33 -> 156482.69 | H14: ='Modelo Runway'!H33 -> 135447.81
A15: EBITDA RECORRENTE PURO (sem FIFA) | B15: ='Modelo Runway'!B34 -> 202173 | C15: ='Modelo Runway'!C34 -> 196411.32 | D15: ='Modelo Runway'!D34 -> 209759.41 | E15: ='Modelo Runway'!E34 -> 184168.73 | F15: ='Modelo Runway'!F34 -> 178200.83 | G15: ='Modelo Runway'!G34 -> 156482.69 | H15: ='Modelo Runway'!H34 -> 135447.81
A16: Margem EBITDA Recorrente Puro | B16: ='Modelo Runway'!B35 -> 0.15235802 | C16: ='Modelo Runway'!C35 -> 0.1372083 | D16: ='Modelo Runway'!D35 -> 0.13727321 | E16: ='Modelo Runway'!E35 -> 0.13403947 | F16: ='Modelo Runway'!F35 -> 0.12579959 | G16: ='Modelo Runway'!G35 -> 0.11969143 | H16: ='Modelo Runway'!H35 -> 0.10416574
A18: ATLETAS (RECEITA E CAPEX)
A19: Receita venda atletas | B19: ='Modelo Runway'!B38 -> 518741 | C19: ='Modelo Runway'!C38 -> 450000 | D19: ='Modelo Runway'!D38 -> 500000 | E19: ='Modelo Runway'!E38 -> 300000 | F19: ='Modelo Runway'!F38 -> 350000 | G19: ='Modelo Runway'!G38 -> 200000 | H19: ='Modelo Runway'!H38 -> 200000
A20: Capex contábil atletas | B20: ='Modelo Runway'!B44 -> -635605 | C20: ='Modelo Runway'!C44 -> -600000 | D20: ='Modelo Runway'!D44 -> -550000 | E20: ='Modelo Runway'!E44 -> -450000 | F20: ='Modelo Runway'!F44 -> -400000 | G20: ='Modelo Runway'!G44 -> -320000 | H20: ='Modelo Runway'!H44 -> -250000
A21: Capex LÍQUIDO (Capex - Vendas) | B21: =-'Modelo Runway'!B44-'Modelo Runway'!B38 -> 116864 | C21: =-'Modelo Runway'!C44-'Modelo Runway'!C38 -> 150000 | D21: =-'Modelo Runway'!D44-'Modelo Runway'!D38 -> 50000 | E21: =-'Modelo Runway'!E44-'Modelo Runway'!E38 -> 150000 | F21: =-'Modelo Runway'!F44-'Modelo Runway'!F38 -> 50000 | G21: =-'Modelo Runway'!G44-'Modelo Runway'!G38 -> 120000 | H21: =-'Modelo Runway'!H44-'Modelo Runway'!H38 -> 50000
A23: CAIXA E VARIAÇÃO
A24: Variação líquida do caixa no ano | B24: ='Modelo Runway'!B54 -> 153167.91 | C24: ='Modelo Runway'!C54 -> -40320.68 | D24: ='Modelo Runway'!D54 -> 33527.413 | E24: ='Modelo Runway'!E54 -> -46663.27 | F24: ='Modelo Runway'!F54 -> 28468.835 | G24: ='Modelo Runway'!G54 -> -42349.31 | H24: ='Modelo Runway'!H54 -> -14884.185
A25: Caixa total inicial | B25: ='Modelo Runway'!B55 -> 242854 | C25: ='Modelo Runway'!C55 -> 242854 | D25: ='Modelo Runway'!D55 -> 202533.32 | E25: ='Modelo Runway'!E55 -> 242854 | F25: ='Modelo Runway'!F55 -> 196190.73 | G25: ='Modelo Runway'!G55 -> 242854 | H25: ='Modelo Runway'!H55 -> 200504.69
A26: CAIXA TOTAL FINAL | B26: ='Modelo Runway'!B56 -> 242854 | C26: ='Modelo Runway'!C56 -> 202533.32 | D26: ='Modelo Runway'!D56 -> 236060.73 | E26: ='Modelo Runway'!E56 -> 196190.73 | F26: ='Modelo Runway'!F56 -> 224659.56 | G26: ='Modelo Runway'!G56 -> 200504.69 | H26: ='Modelo Runway'!H56 -> 185620.5
A28: LEITURA NARRATIVA
A29: Capex / Vendas atletas (= Condição 3) | B29: =IFERROR(-'Modelo Runway'!B44/'Modelo Runway'!B38,0) -> 1.2252839 | C29: =IFERROR(-'Modelo Runway'!C44/'Modelo Runway'!C38,0) -> 1.3333333 | D29: =IFERROR(-'Modelo Runway'!D44/'Modelo Runway'!D38,0) -> 1.1 | E29: =IFERROR(-'Modelo Runway'!E44/'Modelo Runway'!E38,0) -> 1.5 | F29: =IFERROR(-'Modelo Runway'!F44/'Modelo Runway'!F38,0) -> 1.1428571 | G29: =IFERROR(-'Modelo Runway'!G44/'Modelo Runway'!G38,0) -> 1.6 | H29: =IFERROR(-'Modelo Runway'!H44/'Modelo Runway'!H38,0) -> 1.25
A30: Folha ampliada / Receita Recorrente (= Condição 1) | B30: =IFERROR(-'Modelo Runway'!B24/'Modelo Runway'!B15,0) -> 0.53588202 | C30: =IFERROR(-'Modelo Runway'!C24/'Modelo Runway'!C15,0) -> 0.55636385 | D30: =IFERROR(-'Modelo Runway'!D24/'Modelo Runway'!D15,0) -> 0.56290242 | E30: =IFERROR(-'Modelo Runway'!E24/'Modelo Runway'!E15,0) -> 0.55376767 | F30: =IFERROR(-'Modelo Runway'!F24/'Modelo Runway'!F15,0) -> 0.56398765 | G30: =IFERROR(-'Modelo Runway'!G24/'Modelo Runway'!G15,0) -> 0.56566211 | H30: =IFERROR(-'Modelo Runway'!H24/'Modelo Runway'!H15,0) -> 0.58011412
A31: Caixa final / Saídas operacionais mensais (= Condição 4) | B31: =IFERROR('Modelo Runway'!B56/(-'Modelo Runway'!B30/12),0) -> 2.5909332 | C31: =IFERROR('Modelo Runway'!C56/(-'Modelo Runway'!C30/12),0) -> 1.9678212 | D31: =IFERROR('Modelo Runway'!D56/(-'Modelo Runway'!D30/12),0) -> 2.1488002 | E31: =IFERROR('Modelo Runway'!E56/(-'Modelo Runway'!E30/12),0) -> 1.9786931 | F31: =IFERROR('Modelo Runway'!F56/(-'Modelo Runway'!F30/12),0) -> 2.1770312 | G31: =IFERROR('Modelo Runway'!G56/(-'Modelo Runway'!G30/12),0) -> 2.0905838 | H31: =IFERROR('Modelo Runway'!H56/(-'Modelo Runway'!H30/12),0) -> 1.9121961
A33: Notas:
A34: • Toda linha em VERDE puxa do Modelo Runway. Para alterar projeções, edite Premissas Runway.
A35: • Capex LÍQUIDO positivo = consumiu mais caixa em compras do que entrou com vendas; negativo = sobrou caixa.
A36: • Caixa final é o saldo total (livre + restrito) no fim do ano.
A37: • Esta aba é apenas leitura — saída sintética dos 3 cenários.

Sheet Caminho A - Trajetória
A1: Caminho A — Trajetória das 4 Condições nos Cenários
A2: Aplicação das 4 condições de competitividade aos cenários 2026-2027 | Status PASSA/APERTADO/FALHA por condição × ano × cenário
A4: Condição | B4: 2024 (real) | C4: 2025 (real) | D4: OTIMISTA | F4: BASE | H4: PESSIMISTA
D5: 2026 | E5: 2027 | F5: 2026 | G5: 2027 | H5: 2026 | I5: 2027
A7: CONDIÇÃO 1: Folha ampliada / Receita Recorrente | B7: =Indicadores!F7 -> 0.45220225 | C7: =Indicadores!H7 -> 0.53645568 | D7: =IFERROR(-'Modelo Runway'!C24/'Modelo Runway'!C15,0) -> 0.55636385 | E7: =IFERROR(-'Modelo Runway'!D24/'Modelo Runway'!D15,0) -> 0.56290242 | F7: =IFERROR(-'Modelo Runway'!E24/'Modelo Runway'!E15,0) -> 0.55376767 | G7: =IFERROR(-'Modelo Runway'!F24/'Modelo Runway'!F15,0) -> 0.56398765 | H7: =IFERROR(-'Modelo Runway'!G24/'Modelo Runway'!G15,0) -> 0.56566211 | I7: =IFERROR(-'Modelo Runway'!H24/'Modelo Runway'!H15,0) -> 0.58011412
A8: Status | B8: =IF(B7=0,"-",IF(B7<=0.5,"PASSA",IF(B7<=0.65,"APERTADO","FALHA"))) -> PASSA | C8: =IF(C7=0,"-",IF(C7<=0.5,"PASSA",IF(C7<=0.65,"APERTADO","FALHA"))) -> APERTADO | D8: =IF(D7=0,"-",IF(D7<=0.5,"PASSA",IF(D7<=0.65,"APERTADO","FALHA"))) -> APERTADO | E8: =IF(E7=0,"-",IF(E7<=0.5,"PASSA",IF(E7<=0.65,"APERTADO","FALHA"))) -> APERTADO | F8: =IF(F7=0,"-",IF(F7<=0.5,"PASSA",IF(F7<=0.65,"APERTADO","FALHA"))) -> APERTADO | G8: =IF(G7=0,"-",IF(G7<=0.5,"PASSA",IF(G7<=0.65,"APERTADO","FALHA"))) -> APERTADO | H8: =IF(H7=0,"-",IF(H7<=0.5,"PASSA",IF(H7<=0.65,"APERTADO","FALHA"))) -> APERTADO | I8: =IF(I7=0,"-",IF(I7<=0.5,"PASSA",IF(I7<=0.65,"APERTADO","FALHA"))) -> APERTADO
A10: CONDIÇÃO 2: Margem EBITDA Recorrente Puro | B10: =Indicadores!F30 -> 0.18617834 | C10: =Indicadores!H30 -> 0.10215527 | D10: ='Modelo Runway'!C35 -> 0.1372083 | E10: ='Modelo Runway'!D35 -> 0.13727321 | F10: ='Modelo Runway'!E35 -> 0.13403947 | G10: ='Modelo Runway'!F35 -> 0.12579959 | H10: ='Modelo Runway'!G35 -> 0.11969143 | I10: ='Modelo Runway'!H35 -> 0.10416574
A11: Status | B11: =IF(B10=0,"-",IF(B10>=0.1,"PASSA",IF(B10>=0.05,"APERTADO","FALHA"))) -> PASSA | C11: =IF(C10=0,"-",IF(C10>=0.1,"PASSA",IF(C10>=0.05,"APERTADO","FALHA"))) -> PASSA | D11: =IF(D10=0,"-",IF(D10>=0.1,"PASSA",IF(D10>=0.05,"APERTADO","FALHA"))) -> PASSA | E11: =IF(E10=0,"-",IF(E10>=0.1,"PASSA",IF(E10>=0.05,"APERTADO","FALHA"))) -> PASSA | F11: =IF(F10=0,"-",IF(F10>=0.1,"PASSA",IF(F10>=0.05,"APERTADO","FALHA"))) -> PASSA | G11: =IF(G10=0,"-",IF(G10>=0.1,"PASSA",IF(G10>=0.05,"APERTADO","FALHA"))) -> PASSA | H11: =IF(H10=0,"-",IF(H10>=0.1,"PASSA",IF(H10>=0.05,"APERTADO","FALHA"))) -> PASSA | I11: =IF(I10=0,"-",IF(I10>=0.1,"PASSA",IF(I10>=0.05,"APERTADO","FALHA"))) -> PASSA
A13: CONDIÇÃO 3: Capex atletas / Vendas atletas | B13: =Indicadores!F13 -> 3.8628474 | C13: =Indicadores!H13 -> 1.2252839 | D13: =IFERROR(-'Modelo Runway'!C44/'Modelo Runway'!C38,0) -> 1.3333333 | E13: =IFERROR(-'Modelo Runway'!D44/'Modelo Runway'!D38,0) -> 1.1 | F13: =IFERROR(-'Modelo Runway'!E44/'Modelo Runway'!E38,0) -> 1.5 | G13: =IFERROR(-'Modelo Runway'!F44/'Modelo Runway'!F38,0) -> 1.1428571 | H13: =IFERROR(-'Modelo Runway'!G44/'Modelo Runway'!G38,0) -> 1.6 | I13: =IFERROR(-'Modelo Runway'!H44/'Modelo Runway'!H38,0) -> 1.25
A14: Status | B14: =IF(B13=0,"-",IF(B13<=1,"PASSA",IF(B13<=1.5,"APERTADO","FALHA"))) -> FALHA | C14: =IF(C13=0,"-",IF(C13<=1,"PASSA",IF(C13<=1.5,"APERTADO","FALHA"))) -> APERTADO | D14: =IF(D13=0,"-",IF(D13<=1,"PASSA",IF(D13<=1.5,"APERTADO","FALHA"))) -> APERTADO | E14: =IF(E13=0,"-",IF(E13<=1,"PASSA",IF(E13<=1.5,"APERTADO","FALHA"))) -> APERTADO | F14: =IF(F13=0,"-",IF(F13<=1,"PASSA",IF(F13<=1.5,"APERTADO","FALHA"))) -> APERTADO | G14: =IF(G13=0,"-",IF(G13<=1,"PASSA",IF(G13<=1.5,"APERTADO","FALHA"))) -> APERTADO | H14: =IF(H13=0,"-",IF(H13<=1,"PASSA",IF(H13<=1.5,"APERTADO","FALHA"))) -> FALHA | I14: =IF(I13=0,"-",IF(I13<=1,"PASSA",IF(I13<=1.5,"APERTADO","FALHA"))) -> APERTADO
A16: CONDIÇÃO 4: Caixa final / Saídas op. mensais | B16: =Indicadores!F16 -> 1.3995724 | C16: =Indicadores!H16 -> 2.1177358 | D16: =IFERROR('Modelo Runway'!C56/(-'Modelo Runway'!C30/12),0) -> 1.9678212 | E16: =IFERROR('Modelo Runway'!D56/(-'Modelo Runway'!D30/12),0) -> 2.1488002 | F16: =IFERROR('Modelo Runway'!E56/(-'Modelo Runway'!E30/12),0) -> 1.9786931 | G16: =IFERROR('Modelo Runway'!F56/(-'Modelo Runway'!F30/12),0) -> 2.1770312 | H16: =IFERROR('Modelo Runway'!G56/(-'Modelo Runway'!G30/12),0) -> 2.0905838 | I16: =IFERROR('Modelo Runway'!H56/(-'Modelo Runway'!H30/12),0) -> 1.9121961
A17: Status | B17: =IF(B16=0,"-",IF(B16>=2,"PASSA",IF(B16>=1,"APERTADO","FALHA"))) -> APERTADO | C17: =IF(C16=0,"-",IF(C16>=2,"PASSA",IF(C16>=1,"APERTADO","FALHA"))) -> PASSA | D17: =IF(D16=0,"-",IF(D16>=2,"PASSA",IF(D16>=1,"APERTADO","FALHA"))) -> APERTADO | E17: =IF(E16=0,"-",IF(E16>=2,"PASSA",IF(E16>=1,"APERTADO","FALHA"))) -> PASSA | F17: =IF(F16=0,"-",IF(F16>=2,"PASSA",IF(F16>=1,"APERTADO","FALHA"))) -> APERTADO | G17: =IF(G16=0,"-",IF(G16>=2,"PASSA",IF(G16>=1,"APERTADO","FALHA"))) -> PASSA | H17: =IF(H16=0,"-",IF(H16>=2,"PASSA",IF(H16>=1,"APERTADO","FALHA"))) -> PASSA | I17: =IF(I16=0,"-",IF(I16>=2,"PASSA",IF(I16>=1,"APERTADO","FALHA"))) -> APERTADO
A19: TRAJETÓRIA SINTÉTICA — Contagem de condições ATENDIDAS por cenário/ano
A20: Condições PASSA + APERTADO (em 4 totais) | B20: =COUNTIF(B8,"PASSA")+COUNTIF(B8,"APERTADO")+COUNTIF(B11,"PASSA")+COUNTIF(B11,"APERTADO")+COUNTIF(B14,"PASSA")+COUNTIF(B14,"APERTADO")+COUNTIF(B17,"PASSA")+COUNTIF(B17,"APERTADO") -> 3 | C20: =COUNTIF(C8,"PASSA")+COUNTIF(C8,"APERTADO")+COUNTIF(C11,"PASSA")+COUNTIF(C11,"APERTADO")+COUNTIF(C14,"PASSA")+COUNTIF(C14,"APERTADO")+COUNTIF(C17,"PASSA")+COUNTIF(C17,"APERTADO") -> 4 | D20: =COUNTIF(D8,"PASSA")+COUNTIF(D8,"APERTADO")+COUNTIF(D11,"PASSA")+COUNTIF(D11,"APERTADO")+COUNTIF(D14,"PASSA")+COUNTIF(D14,"APERTADO")+COUNTIF(D17,"PASSA")+COUNTIF(D17,"APERTADO") -> 4 | E20: =COUNTIF(E8,"PASSA")+COUNTIF(E8,"APERTADO")+COUNTIF(E11,"PASSA")+COUNTIF(E11,"APERTADO")+COUNTIF(E14,"PASSA")+COUNTIF(E14,"APERTADO")+COUNTIF(E17,"PASSA")+COUNTIF(E17,"APERTADO") -> 4 | F20: =COUNTIF(F8,"PASSA")+COUNTIF(F8,"APERTADO")+COUNTIF(F11,"PASSA")+COUNTIF(F11,"APERTADO")+COUNTIF(F14,"PASSA")+COUNTIF(F14,"APERTADO")+COUNTIF(F17,"PASSA")+COUNTIF(F17,"APERTADO") -> 4 | G20: =COUNTIF(G8,"PASSA")+COUNTIF(G8,"APERTADO")+COUNTIF(G11,"PASSA")+COUNTIF(G11,"APERTADO")+COUNTIF(G14,"PASSA")+COUNTIF(G14,"APERTADO")+COUNTIF(G17,"PASSA")+COUNTIF(G17,"APERTADO") -> 4 | H20: =COUNTIF(H8,"PASSA")+COUNTIF(H8,"APERTADO")+COUNTIF(H11,"PASSA")+COUNTIF(H11,"APERTADO")+COUNTIF(H14,"PASSA")+COUNTIF(H14,"APERTADO")+COUNTIF(H17,"PASSA")+COUNTIF(H17,"APERTADO") -> 3 | I20: =COUNTIF(I8,"PASSA")+COUNTIF(I8,"APERTADO")+COUNTIF(I11,"PASSA")+COUNTIF(I11,"APERTADO")+COUNTIF(I14,"PASSA")+COUNTIF(I14,"APERTADO")+COUNTIF(I17,"PASSA")+COUNTIF(I17,"APERTADO") -> 4
A21: Condições em FALHA | B21: =COUNTIF(B8,"FALHA")+COUNTIF(B11,"FALHA")+COUNTIF(B14,"FALHA")+COUNTIF(B17,"FALHA") -> 1 | C21: =COUNTIF(C8,"FALHA")+COUNTIF(C11,"FALHA")+COUNTIF(C14,"FALHA")+COUNTIF(C17,"FALHA") -> 0 | D21: =COUNTIF(D8,"FALHA")+COUNTIF(D11,"FALHA")+COUNTIF(D14,"FALHA")+COUNTIF(D17,"FALHA") -> 0 | E21: =COUNTIF(E8,"FALHA")+COUNTIF(E11,"FALHA")+COUNTIF(E14,"FALHA")+COUNTIF(E17,"FALHA") -> 0 | F21: =COUNTIF(F8,"FALHA")+COUNTIF(F11,"FALHA")+COUNTIF(F14,"FALHA")+COUNTIF(F17,"FALHA") -> 0 | G21: =COUNTIF(G8,"FALHA")+COUNTIF(G11,"FALHA")+COUNTIF(G14,"FALHA")+COUNTIF(G17,"FALHA") -> 0 | H21: =COUNTIF(H8,"FALHA")+COUNTIF(H11,"FALHA")+COUNTIF(H14,"FALHA")+COUNTIF(H17,"FALHA") -> 1 | I21: =COUNTIF(I8,"FALHA")+COUNTIF(I11,"FALHA")+COUNTIF(I14,"FALHA")+COUNTIF(I17,"FALHA") -> 0
A23: Notas:
A24: • Esta aba aplica as 4 Condições aos cenários do Modelo Runway, materializando o eixo 'Hegemonia condicional'.
A25: • Critérios iguais à aba Indicadores: limite 65% (COND 1), 5% (COND 2), 1,0x (COND 3), 1 mês (COND 4).
A26: • PASSA verde = margem confortável; APERTADO amarelo = no limite; FALHA vermelho = condição não atendida.
A27: • Linha 20: contagem total das condições em PASSA + APERTADO (4 = todas atendidas; 0 = todas falharam).
A28: • A degradação do número de condições atendidas, à medida que o cenário piora, é a evidência empírica do eixo do post.
A29: • Em cenário Pessimista, o número de condições atendidas tende a cair — particularmente CONDIÇÃO 1 (folha já contratada) e CONDIÇÃO 2 (EBITDA Puro encolhe sem premiações).
A30: • Reais 2024 e 2025 puxam de Indicadores (Consol). Cenários puxam de Modelo Runway.

Sheet Hilton Rio By Yoo
A1: Saga Imobiliária — Hilton Santos / Rio By Yoo
A2: Histórico das 46 unidades entregues pela Cyrela em set/2021 | Valores em R$ milhares
A4: Indicador | B4: 2021 | C4: 2022 | D4: 2023 | E4: 2024 | F4: 2025 | G4: Evento
A5: Unidades originais entregues (Cyrela) | B5: 46 | C5: 46 | D5: 46 | E5: 46 | F5: 46 | G5: Entrega set/2021
A6: Unidades vendidas no ano | B6: 0 | C6: 0 | D6: ≈4 | E6: 7 | F6: 12 | G6: Liquidação acelerada
A7: Saldo de unidades remanescentes | B7: 46 | C7: 46 | D7: 42 | E7: 35 | F7: 23 | G7: Restam 23 em 2025
A9: VALORES (R$ MILHARES)
A10: Indicador | B10: 2021 | C10: 2022 | D10: 2023 | E10: 2024 | F10: 2025 | G10: Observação
A11: Custo total das unidades (origem) | B11: 104000 | G11: Cyrela 2021
A12: Valor justo total (avaliação) | B12: 165000 | G12: Mark-to-market 2021
A13: Receita de vendas no ano | B13: 0 | C13: 0 | E13: 24396 | F13: 34167 | G13: NE 6
A14: Ganho reconhecido em 'Outras receitas op.' | B14: 0 | C14: 0 | E14: 8158 | F14: 7010 | G14: Não-recorrente
A15: Margem do ganho (ganho/receita) | E15: 0.334 | F15: 0.205 | G15: Margem caiu
A17: SALDOS NO BP
A18: Linha do BP | B18: 2021 | C18: 2022 | D18: 2023 | E18: 2024 | F18: 2025 | G18: Observação
A19: Propriedades para investimento | B19: 104911 | C19: 104893 | D19: 38625 | E19: 171 | F19: 0 | G19: Reclassif. gradual
A20: Ativo disponível para venda | B20: 0 | C20: 0 | D20: 59953 | E20: 81377 | F20: 54220 | G20: Movimento 2023
A21: Total Hilton no BP | B21: 104911 | C21: 104893 | D21: 98578 | E21: 81548 | F21: 54220
A22: Valor justo do saldo remanescente | E22: 121200 | F22: 73914 | G22: NE 6
A23: Ganho latente (Valor justo − Custo BP) | E23: 39823 | F23: 19694 | G23: Não-recorrente futuro
A25: Notas:
A26: • Hilton Santos / Rio By Yoo: edifício no centro do Rio cedido como parte do Acordo BACEN (multas cambiais 1990-1998).
A27: • 46 unidades entregues pela Cyrela em set/2021 (custo R$ 104 mi, valor justo R$ 165 mi inicial).
A28: • Inicialmente classificado como 'Propriedades para investimento' (BP linha 22).
A29: • Em ago/2023, 26 unidades reclassificadas para 'Ativo disponível para venda' — início da estratégia de liquidação.
A30: • Em 2024: 7 unidades vendidas, ganho R$ 8.158 mi reconhecido em 'Outras receitas operacionais'.
A31: • Em 2025: 12 unidades vendidas (mais que o dobro de 2024). Margem do ganho caiu de 33% para 20% — descontos para acelerar liquidação.
A32: • Saldo 2025: 23 unidades remanescentes a custo R$ 54.220 e valor justo R$ 73.914 — ganho latente R$ 19,7 mi.
A33: • Ritmo de venda 2024-2025: ~10 unidades/ano. Liquidação total esperada em 2-3 anos.
A34: • Para Operacional Puro: ganhos Hilton entram como ajuste não-recorrente (linha 15 da aba).

Sheet PROFUT-PERSE
A1: Parcelamentos Fiscais — PROFUT (Lei 13.155) + PERSE (Lei 14.148)
A2: Cronograma e composição dos parcelamentos de tributos federais | R$ milhares
A4: Componente | B4: 2022 | C4: 2023 | D4: 2024 | E4: 2025 | F4: Status 2025
A6: LEI 13.155 — PROFUT (parcelamento original)
A7: IRRF parcelado | C7: 51435 | D7: 49945 | E7: 48699 | F7: HOMOLOGADO 2025
A8: INSS parcelado | C8: 69503 | D8: 67489 | E8: 65806 | F8: HOMOLOGADO
A9: FGTS parcelado | C9: 7307 | D9: 7192 | E9: 5590 | F9: HOMOLOGADO
A10: Subtotal PROFUT | C10: 128245 | D10: 124626 | E10: 120095
A12: LEI 14.148 — PERSE (reparcelamento ago/2023)
A13: IRRF migrado | C13: 38907 | D13: 40732 | E13: 42221 | F13: HOMOLOGADO
A14: Subtotal PERSE | C14: 38907 | D14: 40732 | E14: 42221
A16: TOTAL PARCELAMENTOS PROFUT + PERSE | B16: 244834 | C16: 167152 | D16: 165358 | E16: 162316
A18: EFEITO NÃO-RECORRENTE DO REPARCELAMENTO PERSE (ago/2023)
A19: Em ago/2023, parte do parcelamento PROFUT (IRRF) foi migrada para PERSE com desconto
A21: Linha de impacto | B21: Valor
A22: Desconto em 'Outras receitas operacionais' | B22: 19440 | F22: Não-recorrente
A23: Desconto em 'Receitas financeiras' | B23: 27887 | F23: Não-recorrente
A24: Desconto total PERSE 2023 | B24: 47327
A26: CRONOGRAMA DE PAGAMENTOS LP (NE 10 do balanço 2025)
A27: Período | B27: Valor a pagar
A28: 2026 | B28: 15832 | F28: Anual
A29: 2027 | B29: 15832 | F29: Anual
A30: 2028-2035 (somatório) | B30: 130652 | F30: ~16/ano
A31: Total LP a pagar | B31: 162316
A33: Notas:
A34: • PROFUT (Lei 13.155/2015): programa de parcelamento de tributos federais para clubes de futebol — IRRF, INSS, FGTS.
A35: • PERSE (Lei 14.148/2021): Programa Emergencial de Retomada do Setor de Eventos — concedeu redução de tributos e benefícios fiscais.
A36: • Em ago/2023, parte do parcelamento de IRRF foi migrada para PERSE com desconto, gerando R$ 47,3 mi de efeito positivo único na DRE 2023 (R$ 19 mi em Outras receitas op. + R$ 28 mi em Receitas financeiras).
A37: • Em 2025: TODAS as obrigações foram HOMOLOGADAS. Confirmação literal da NE 10. Esse é o motivo de o parecer EY 2025 não trazer parágrafos de ênfase.
A38: • Total dos parcelamentos vem caindo modestamente: R$ 167 mi (2023) → R$ 162 mi (2025). A correção monetária quase compensa o pagamento.
A39: • Cronograma 2026 e 2027: R$ 15.832/ano cada — input fixo no Modelo Runway.
A40: • Total 2022 (R$ 244.834) é estimativa: handoff dá detalhamento só a partir de 2023.

Sheet Gasômetro
A1: Projeto Estádio — Terreno Gasômetro
A2: Histórico da aquisição do terreno na Av. São Cristóvão nº 1200 | R$ milhares
A4: LINHA DO TEMPO
A5: Data | B5: Evento | C5: Valor | D5: Status
A6: 02/08/2024 | B6: Homologação do leilão | D6: Marco inicial
A7: 02/09/2024 | B7: Pagamento principal | C7: 138195 | D7: Pago
A8: 23/09/2024 | B8: Pagamento adicional (perícia judicial) | C8: 7885 | D8: Pago
A9: 31/12/2024 | B9: Saldo classificado como 'Terreno em processo' | C9: 146080 | D9: BP linha 23
A10: 18/12/2025 | B10: Termo de Acordo Definitivo com CEF + CCPAR + União + Município | D10: Audiências finalizadas
A11: 2026 (esperado) | B11: Reclassificação para 'Terreno' definitivo | C11: 146080 | D11: Após formalização
A14: STATUS NO BP
A15: Linha | B15: 2024 | C15: 2025 | D15: Observação
A16: 'Terreno em processo de aquisição' (BP-Imobilizado) | B16: 146080 | C16: 146080 | D16: Aguarda reclassificação
A18: CITAÇÃO LITERAL DA NE 8 DO BALANÇO 2025
A19: "Em 18 de dezembro de 2025, as partes — CRF, CEF, Caixa FII Porto Maravilha, União Federal, Município do RJ e CCPAR —, após uma série de audiências, realizaram ajustes finais com vistas à celebração do Termo de Acordo Definitivo que garantirá ao CRF a posse definitiva do terreno."
A24: Notas:
A25: • Gasômetro: terreno na Av. São Cristóvão nº 1200, em frente à antiga sede do gás.
A26: • Aquisição em duas parcelas em set/2024 (R$ 138 mi + R$ 7,9 mi de perícia) = R$ 146,08 mi total.
A27: • Processo judicial 0900053-11.2024.8.19.0001.
A28: • Está classificado em 'Terreno em processo de aquisição' (não em 'Terreno' definitivo) porque ainda dependia da formalização do Termo de Acordo entre as 6 partes envolvidas.
A29: • Em 18/dez/2025: audiências finalizadas, ajustes finais feitos — Termo de Acordo Definitivo a ser celebrado em 2026.
A30: • Em 2026, a reclassificação para 'Terreno' definitivo será feita no BP, sem impacto em P&L.
A31: • Implicação prospectiva: a partir de 2026, o Flamengo pode iniciar projeto de construção do próprio estádio. Capex estimado: R$ 2-3 bilhões ao longo de 4-6 anos — NÃO modelado no runway base.
A38: A Fla-Flu Serviços S.A. é tributada por lucro presumido (não lucro real).

Sheet Maracana Fla-Flu
A1: Concessão Maracanã — Fla-Flu Serviços S.A.
A2: Primeiro ano completo de operação consolidada (2025) | R$ milhares
A4: ESTRUTURA SOCIETÁRIA
A5: Item | B5: Valor | C5: Observação
A6: Constituição | B6: 30/08/2024 | C6: Sociedade anônima
A7: Participação Flamengo | B7: 0.65 | C7: Controladora
A8: Participação Fluminense | B8: 0.35 | C8: Não-controlador
A9: Capital social total | B9: 20061 | C9: 31/12/2024
A10: Capital integralizado até 31/12/2025 | B10: 9024 | C10: Falta R$ 11.037 mi
A11: Falta integralizar pelo Flamengo até ago/2028 | B11: 7174 | C11: 65% × 11.037
A13: CONTRATO DE CONCESSÃO MARACANÃ
A14: Item | B14: Valor | C14: Observação
A15: Contrato SECC nº 033/2024 | B15: 27/09/2024 | C15: Assinatura
A16: Prazo da concessão | B16: 20 anos | C16: Até nov/2044
A17: Montante TOTAL a pagar (nominal) | B17: 401218 | C17: 80 parcelas trimestrais + IPCA
A18: Valor PRESENTE reconhecido (BP) | B18: 178084 | C18: Setembro/2024
A19: Amortização anual estimada (linear) | B19: 8900 | C19: Linha NOVA na DFC 2025
A20: Saída de caixa anual aproximada | B20: 20000 | C20: + IPCA
A22: RESULTADOS FLA-FLU SERVIÇOS S.A.
A23: Item | B23: 2024 (parcial) | C23: 2025 (completo) | D23: Δ
A24: Ativo total | C24: 245137
A25: Passivo total | C25: 235306
A26: Patrimônio líquido | B26: 3695 | C26: 9831 | D26: 6136
A27: Receita bruta total (estádio + tour) | B27: 16711 | C27: 116400 | D27: 99689 | E27: +597%
A28: Resultado do exercício | B28: -5330 | C28: 21445 | D28: 26775 | E28: Inversão
A30: EQUIVALÊNCIA E DIVIDENDOS (perspectiva Flamengo)
A31: Item | B31: 2024 | C31: 2025 | D31: Acumulado
A32: Equivalência patrimonial Cont (65% × resultado) | B32: -3465 | C32: 13939 | D32: 10474 | E32: DRE!17
A33: Dividendo declarado pela Fla-Flu (total) | B33: 0 | C33: 15309 | D33: 15309 | E33: Payout 71%
A34: Dividendo a receber pelo Flamengo (65%) | B34: 0 | C34: 9951 | D34: 9951 | E34: C/R no BP
A35: Dividendo pago em caixa em 2025 | B35: 0 | C35: 0 | D35: 0 | E35: Não circulou
A37: IR/CSLL DA FLA-FLU (LUCRO PRESUMIDO)
A38: A Fla-Flu Serviços S.A. é tributada por lucro presumido (não lucro real).
A40: Tributo | B40: 2024 | C40: 2025 | D40: Crescimento
A41: IRPJ/CSLL | B41: 2494 | C41: 4025 | D41: 0.614 | E41: +61%
A42: PIS/COFINS | B42: 367 | C42: 450 | D42: 0.226 | E42: +23%
A43: Total IR + PIS/COFINS no Consol | B43: 2861 | C43: 4475
A44: IR/CSLL total no DRE Consol (linha 27) | B44: 2546 | C44: 14706 | E44: Diferença = ajustes
A46: Notas:
A47: • Fla-Flu Serviços S.A.: sociedade anônima constituída em 30/08/2024 — Flamengo 65% + Fluminense 35%.
A48: • Gestora do Maracanã sob contrato de concessão SECC nº 033/2024 (20 anos, até nov/2044).
A49: • Tributação: LUCRO PRESUMIDO (não lucro real) — primeiro grande imposto sobre operação consolidada do Flamengo.
A50: • Primeiro ano completo (2025): resultado positivo de R$ 21,4 mi (vs déficit R$ 5,3 mi em 2024 parcial). Inversão significativa.
A51: • Primeiro dividendo declarado: R$ 15,3 mi total (payout 71% sobre lucro). Flamengo tem R$ 9,95 mi a receber — mas NÃO circulou em caixa em 2025 (entrou em C/R no BP).
A52: • Falta R$ 7,2 mi do Flamengo a integralizar até ago/2028 (65% dos R$ 11 mi restantes do capital subscrito).
A53: • Outorga de concessão: passivo de R$ 401 mi nominal (R$ 178 mi a valor presente) — único passivo de longo prazo no Consolidado.
A54: • Linha NOVA na DFC 2025 (Consol): amortização da outorga (R$ 9,4 mi anual) + pagamento de R$ 20 mi de caixa.

Sheet Exposicao Cambial
A1: Exposição Cambial
A2: Histórico do risco cambial e estreia do hedge em 2025 | R$ milhares
A4: EXPOSIÇÃO CAMBIAL (passivo - ativo em ME, % do passivo total)
A5: Métrica | B5: 2022 | C5: 2023 | D5: 2024 | E5: 2025
A6: % do passivo bruto em ME / passivo total | C6: 0.31 | D6: 0.67 | F6: Métrica 2024
A7: Exposição líquida (P-A em ME) — SEM hedge | D7: 0.19 | E7: 0.12 | F7: NE 23.2.d
A8: Exposição líquida AJUSTADA pelo hedge | D8: 0.19 | E8: 0.02 | F8: Apenas 2025
A10: VARIAÇÃO CAMBIAL NO RESULTADO FINANCEIRO (R$ milhares)
A11: Componente | B11: 2022 | C11: 2023 | D11: 2024 | E11: 2025
A12: Variação cambial — Despesa financeira | D12: -35302 | E12: 0 | F12: NE 20
A13: Variação cambial — Receita financeira | C13: 8062 | D13: 0 | E13: 10820 | F13: NE 20
A14: Variação cambial LÍQUIDA | C14: 8062 | D14: -35302 | E14: 10820 | F14: Swing +46 mi
A16: HEDGE CAMBIAL 2025 — ESTREIA (NE 23.2.d)
A17: Item | B17: Moeda | C17: Nocional | D17: Vencimento | E17: Contraparte
A18: Forwards USD | B18: USD | C18: 9183 | D18: Fev-Ago/2026 | E18: Banco Itaú Unibanco
A19: Forwards EUR | B19: EUR | C19: 7225 | D19: Mai-Jul/2026 | E19: Banco BTG Pactual
A20: ETFs cambiais (USD) — também usados como proteção econômica
A22: EFEITO DO HEDGE NO RESULTADO 2025
A23: Componente | B23: Valor | C23: Local
A24: AVP forwards (receita financeira) | B24: 8164 | C24: NE 20
A25: Resultado líquido valor justo forwards | B25: 3086 | C25: Ativo Circulante (BP) + Receita fin.
A26: IOF adicional 2025 vs 2024 (custo do hedge) | B26: -8437 | C26: Despesa financeira
A27: Efeito líquido do hedge no DRE 2025 | B27: 2813 | C27: Soma
A29: MUDANÇA DE POSTURA (2024 → 2025)
A30: Em 2024, a Administração admitia explicitamente a falta de hedge como 'ponto de atenção relevante' (NE 24.2.d 2024): 'não possui instrumentos financeiros derivativos contratados como forma de proteção.' Em 2025, estreia carteira de forwards USD+EUR e adota ETFs cambiais como proteção econômica.
A35: Notas:
A36: • Métrica '% passivo bruto em ME / passivo total' (linha 6) é a do RG 2024 — comparação com 2025 não direta.
A37: • Métrica '% passivo líquido em ME / passivo total' (linha 7) é a da NE 23.2.d — comparável entre anos.
A38: • Estreia do hedge cambial em 2025 reduziu a exposição líquida ajustada de 19% (2024) para 2% (2025).
A39: • Carteira de forwards expira entre fev e ago/2026 — exige rolagem contínua para manter cobertura.
A40: • Apreciação do real em 2025 explica boa parte do swing de R$ 46 mi no resultado financeiro vs 2024.
A41: • Efeito líquido do hedge em si no DRE 2025: positivo R$ 2,8 mi — o hedge praticamente não moveu a agulha do resultado. O ganho cambial veio da apreciação direta do real, não do hedge.
A42: • Para a aba Operacional Puro, a variação cambial NÃO entra como não-recorrente — está no resultado financeiro (abaixo do EBITDA).

Sheet Recebiveis Inadimplencias
A1: Recebíveis e Inadimplências
A2: C/R jogadores + aging + casos de inadimplência | R$ milhares
A4: CONTAS A RECEBER DE JOGADORES — Evolução
A5: Saldo no BP | B5: 2022 | C5: 2023 | D5: 2024 | E5: 2025
A6: C/R jogadores CP | B6: 53821 | C6: 123423 | D6: 112967 | E6: 278998
A7: C/R jogadores LP | B7: 37034 | C7: 54196 | D7: 36066 | E7: 107905
A8: Total C/R jogadores (Consol) | B8: 90855 | C8: 177619 | D8: 149033 | E8: 386903 | F8: +159% em 2025
A10: TOP 3 DEVEDORES DE JOGADORES — 31/12/2025 (NE 4)
A11: Devedor | B11: Atleta | C11: Saldo | D11: % Total
A12: AS Roma (Itália) | B12: Wesley Vinicius França | C12: 94672 | D12: 0.244 | E12: (Cont)
A13: Everton FC (Inglaterra) | B13: Carlos Alcaraz | C13: 60031 | D13: 0.155 | E13: (Cont)
A14: Al-Ahli Club Company (Arábia) | B14: Matheus Gonçalves | C14: 34268 | D14: 0.089 | E14: (Cont)
A15: Top 3 | C15: 188971 | D15: 0.488 | E15: ≈49% do total
A17: AGING CONSOLIDADO DOS C/R
A18: Faixa | B18: 2024 | C18: 2025 | D18: Δ | E18: % 2025
A19: A vencer | B19: 130577 | C19: 250357 | D19: 119780 | E19: 0.554
A20: 1-30 dias vencido | B20: 44895 | C20: 141284 | D20: 96389 | E20: 0.312
A21: 31-90 dias | B21: 15583 | C21: 18231 | D21: 2648 | E21: 0.04
A22: 91-180 dias | B22: 26304 | C22: 7567 | D22: -18737 | E22: 0.017
A23: Acima de 180 dias | B23: 48448 | C23: 71989 | D23: 23541 | E23: 0.159
A24: Total | B24: 265807 | C24: 489428 | D24: 223621 | E24: 1
A26: PCLD (Provisão para Créditos de Liquidação Duvidosa)
A27: Item | B27: 2024 | C27: 2025 | D27: Δ
A28: Saldo de PCLD no BP | B28: 40240 | C28: 37114 | D28: -3126 | E28: Reversão líquida
A29: PCLD reconhecido no exercício | B29: 7336 | C29: -3126 | D29: -10462 | E29: Recuperação parcial
A31: CASOS DE INADIMPLÊNCIA RELATADOS NAS NE
A32: Caso | B32: Detalhe | C32: Status 2024 | D32: Status 2025
A33: Matheus França → Corinthians | B33: EUR 4.000 | C33: 1ª parcela em mora 05/08/2024 | D33: Em cobrança via Brax
A34: Thiago Maia → Internacional | B34: EUR 4.000 | C34: 3 parcelas inadimplentes | D34: Renegociado 6 parcelas até 08/2027
A35: André Luiz → CFEA Estrela | B35: EUR 500 | C35: 1ª parcela em atraso | D35: —
A36: Werton → Leixões | B36: EUR 1.000 | C36: 1ª parcela em atraso | D36: —
A38: CONCENTRAÇÃO DE C/R — RISCO DE CRÉDITO
A39: Em 2025, 49% do total de C/R jogadores está concentrado em 3 devedores externos (Roma, Everton, Al-Ahli). Combinado com o crescimento de 159% do estoque total e o aumento da faixa '1-30 dias vencido' (de R$ 44,9 para R$ 141,3 mi), configura-se exposição material a risco de crédito internacional, especialmente em moedas EUR e USD.
A44: Notas:
A45: • C/R jogadores cresceu 159% entre 2024 e 2025 (R$ 149 → R$ 387 mi) — caixa futuro das vendas de Wesley, Alcaraz e Matheus Gonçalves.
A46: • Top 3 devedores externos (Roma, Everton, Al-Ahli) concentram quase metade do estoque — risco de crédito internacional material.
A47: • PCLD virou positivo R$ 3,1 mi em 2025 (vs R$ 7,3 mi de constituição em 2024) — recuperação parcial das inadimplências relatadas.
A48: • Aging mostra o aumento expressivo da faixa '1-30 dias vencido' — R$ 141 mi em 2025 (vs R$ 45 mi em 2024). Provavelmente parcelas das vendas recentes que entraram em atraso.
A49: • Caso Matheus França: 1ª parcela em mora desde 05/08/2024 — Brax (intermediadora) foi acionada para cobrança. Sem progresso reportado em 2025.
A50: • Caso Thiago Maia: renegociado para 6 parcelas até 30/08/2027 — provavelmente está atrás do aumento da faixa '>180 dias' em R$ 23,5 mi.
A51: • Caso Olávio Jr. (jan/2026): vendido ao Club Universidad Nacional do México por USD 5.000 — adiantamento de R$ 6.794 mi já recebido em 2025 (NE 12).
